{
  "timestamp": "2026-05-18T07:55:39.614021",
  "companies": {
    "tencent": {
      "price": 448.4,
      "open": 455.0,
      "high": 457.8,
      "low": 445.8,
      "volume": 26145563,
      "turnover": 11723670449.199999,
      "change": -8.0,
      "change_pct": -1.75285,
      "amplitude": 2.6761819803746656,
      "ma_5": 453.7813781738281,
      "ma_10": 459.0260955810547,
      "ma_20": 472.0127014160156,
      "ma_50": 493.4852734375,
      "ma_200": 496.26531982421875,
      "ema_12": 461.2646521780037,
      "ema_26": 473.23602353045976,
      "rsi_14": 35.938784051927314,
      "rsi_6": 21.883384071156,
      "macd": -11.97137135245606,
      "macd_signal": -10.774234217210454,
      "macd_histogram": -1.1971371352456064,
      "bb_upper": 509.90508358603046,
      "bb_middle": 472.0127014160156,
      "bb_lower": 434.12031924600075,
      "bb_width": 16.055662085507237,
      "atr": 11.582031530831282,
      "volatility": 24.321772299933322,
      "historical_vol_20": 24.321772299933322,
      "historical_vol_60": 0.0,
      "momentum_10": -3.93387290925554,
      "stoch_k": 8.594052102185628,
      "stoch_d": 8.594052102185628,
      "williams_r": -91.40594789781439,
      "52w_high": 552.06787109375,
      "52w_low": 448.3999938964844,
      "52w_position": 0.0,
      "avg_volume_20": 27827668.8,
      "volume_ratio": 0.941180635296335,
      "support_levels": [
        448.3999938964844
      ],
      "resistance_levels": [
        516.4824829101562
      ],
      "market_cap_billion": 537,
      "market_cap_display": "$537B",
      "market_cap_hkd": "HK$4192B",
      "pe_ratio": 11.721033,
      "pb_ratio": 3.123004,
      "ps_ratio": 5.274844,
      "peg_ratio": 1.36,
      "ev_ebitda": 14.706,
      "fcf_yield": 24.201931935867037,
      "roe": 20.515,
      "roa": 7.9169996000000005,
      "gross_margin": 56.449000000000005,
      "op_margin": 34.294999999999995,
      "net_margin": 30.606002,
      "revenue_growth": 9.1,
      "earnings_growth": 22.900000000000002,
      "revenue_billion": 768.201981952,
      "debt_equity": 0.33468000000000003,
      "cash_billion": 459.714985984,
      "net_cash_billion": 54.203973632,
      "fcf_billion": 130.08662528,
      "dividend_yield": 115.99999999999999,
      "beta": 0.753,
      "eps": 27.84,
      "source": {
        "quote": "akshare",
        "ohlcv": "yfinance",
        "fundamentals": "yfinance"
      },
      "confidence": {
        "quote": 0.95,
        "ohlcv": 0.85,
        "fundamentals": 0.8
      },
      "source_timestamp": "2026-05-18T07:52:35.748093",
      "last_verified_at": "2026-05-18T07:52:37.940105",
      "is_estimated": false,
      "estimated_fields": [],
      "company_name": "Tencent",
      "symbol": "00700",
      "industry": "Technology / Gaming / Social Media",
      "sector": "Communication Services",
      "technical_rating": {
        "score": -3,
        "rating": "Sell",
        "color": "#F44336",
        "signals": [
          "Trend bearish",
          "MACD negative"
        ]
      },
      "derivative_analysis": {
        "daily_expected_move": 6.870060345229386,
        "atr_percent": 2.5829686732451567,
        "support_level": 448.3999938964844,
        "resistance_level": 516.4824829101562,
        "tight_stop_loss": 431.02695270375307,
        "target_1r": 465.7730472962469,
        "target_2r": 483.1460945924938,
        "risk_reward_ratio": "1:2"
      },
      "expert_commentary": {
        "technical": "Tencent RSI 35.9, MACD -11.97, trend bearish.",
        "volatility": "Annualized volatility 24.3% with ATR 2.6%.",
        "derivative": "Expected daily move HK$6.87; support HK$448.40, resistance HK$516.48."
      },
      "stale": false
    },
    "alibaba": {
      "price": 131.4,
      "open": 130.4,
      "high": 134.9,
      "low": 128.6,
      "volume": 87615042,
      "turnover": 11512616518.800001,
      "change": -0.9,
      "change_pct": -0.68027,
      "amplitude": 4.794520547945214,
      "ma_5": 133.52000122070314,
      "ma_10": 134.67999877929688,
      "ma_20": 132.93999938964845,
      "ma_50": 129.7739993286133,
      "ma_200": 131.7482752306708,
      "ema_12": 133.3429165193304,
      "ema_26": 132.34881831231294,
      "rsi_14": 51.143458068445696,
      "rsi_6": 28.491602967539663,
      "macd": 0.9940982070174584,
      "macd_signal": 0.8946883863157126,
      "macd_histogram": 0.09940982070174587,
      "bb_upper": 140.35926972043336,
      "bb_middle": 132.93999938964845,
      "bb_lower": 125.52072905886354,
      "bb_width": 11.161832954487922,
      "atr": 5.499998910086496,
      "volatility": 43.780683822267804,
      "historical_vol_20": 43.780683822267804,
      "historical_vol_60": 0.0,
      "momentum_10": 0.0762241660379588,
      "stoch_k": 29.444461398654514,
      "stoch_d": 29.444461398654514,
      "williams_r": -70.55553860134549,
      "52w_high": 152.1999969482422,
      "52w_low": 118.5,
      "52w_position": 37.98220834089858,
      "avg_volume_20": 77775975.0,
      "volume_ratio": 1.1265283656039027,
      "support_levels": [
        126.0
      ],
      "resistance_levels": [
        140.89999389648438
      ],
      "market_cap_billion": 395,
      "market_cap_display": "$395B",
      "market_cap_hkd": "HK$3087B",
      "pe_ratio": 13.588821,
      "pb_ratio": 2.0385623,
      "ps_ratio": 2.4616945,
      "peg_ratio": 0.45,
      "ev_ebitda": 24.464,
      "fcf_yield": -11.748625683474206,
      "roe": 9.2159994,
      "roa": 2.0079998000000003,
      "gross_margin": 39.811,
      "op_margin": -0.348,
      "net_margin": 10.12,
      "revenue_growth": 2.9000000000000004,
      "earnings_growth": 100.49999999999999,
      "revenue_billion": 1023.67002624,
      "debt_equity": 0.25232,
      "cash_billion": 316.893986816,
      "net_cash_billion": 32.712982528,
      "fcf_billion": -46.5110016,
      "dividend_yield": 78.0,
      "beta": 0.494,
      "eps": 6.34,
      "source": {
        "quote": "akshare",
        "ohlcv": "yfinance",
        "fundamentals": "yfinance"
      },
      "confidence": {
        "quote": 0.95,
        "ohlcv": 0.85,
        "fundamentals": 0.8
      },
      "source_timestamp": "2026-05-18T07:54:22.106182",
      "last_verified_at": "2026-05-18T07:54:23.253569",
      "is_estimated": false,
      "estimated_fields": [],
      "company_name": "Alibaba",
      "symbol": "09988",
      "industry": "E-commerce / Cloud",
      "sector": "Consumer Discretionary",
      "technical_rating": {
        "score": 1,
        "rating": "Hold",
        "color": "#FF9800",
        "signals": [
          "MACD positive"
        ]
      },
      "derivative_analysis": {
        "daily_expected_move": 3.623911936461884,
        "atr_percent": 4.185691712394593,
        "support_level": 126.0,
        "resistance_level": 140.89999389648438,
        "tight_stop_loss": 123.15000163487026,
        "target_1r": 139.64999836512976,
        "target_2r": 147.8999967302595,
        "risk_reward_ratio": "1:2"
      },
      "expert_commentary": {
        "technical": "Alibaba RSI 51.1, MACD 0.99, trend bearish.",
        "volatility": "Annualized volatility 43.8% with ATR 4.2%.",
        "derivative": "Expected daily move HK$3.62; support HK$126.00, resistance HK$140.90."
      },
      "stale": false
    },
    "xiaomi": {
      "price": 30.68,
      "open": 31.0,
      "high": 31.06,
      "low": 30.14,
      "volume": 99597194,
      "turnover": 3055641911.92,
      "change": -0.02,
      "change_pct": -0.06515,
      "amplitude": 2.998696219035196,
      "ma_5": 31.27599983215332,
      "ma_10": 31.21599998474121,
      "ma_20": 31.111000061035156,
      "ma_50": 32.07159999847412,
      "ma_200": 32.44206902076458,
      "ema_12": 31.139549673875607,
      "ema_26": 31.38378314285998,
      "rsi_14": 47.47474990734187,
      "rsi_6": 21.17649698751248,
      "macd": -0.2442334689843726,
      "macd_signal": -0.21981012208593534,
      "macd_histogram": -0.024423346898437254,
      "bb_upper": 32.71387125816453,
      "bb_middle": 31.111000061035156,
      "bb_lower": 29.508128863905785,
      "bb_width": 10.304208762076293,
      "atr": 1.1557143075125558,
      "volatility": 36.63243961996047,
      "historical_vol_20": 36.63243961996047,
      "historical_vol_60": 0.0,
      "momentum_10": 0.7879241158255338,
      "stoch_k": 46.56864395052863,
      "stoch_d": 46.56864395052863,
      "williams_r": -53.43135604947137,
      "52w_high": 36.560001373291016,
      "52w_low": 29.020000457763672,
      "52w_position": 22.281168450737287,
      "avg_volume_20": 139920976.85,
      "volume_ratio": 0.713444089995288,
      "support_levels": [
        29.020000457763672
      ],
      "resistance_levels": [
        32.400001525878906
      ],
      "market_cap_billion": 95,
      "market_cap_display": "$95B",
      "market_cap_hkd": "HK$745B",
      "pe_ratio": 16.641146,
      "pb_ratio": 2.597885,
      "ps_ratio": 1.7324127,
      "peg_ratio": 2.41,
      "ev_ebitda": 18.819,
      "fcf_yield": 16.926038618957943,
      "roe": 18.25,
      "roa": 4.441,
      "gross_margin": 22.263001,
      "op_margin": 2.181,
      "net_margin": 9.1070004,
      "revenue_growth": 7.3,
      "earnings_growth": -33.7,
      "revenue_billion": 457.286680576,
      "debt_equity": 0.15709,
      "cash_billion": 107.696586752,
      "net_cash_billion": 65.858691072,
      "fcf_billion": 16.177907712,
      "dividend_yield": 0.1,
      "beta": 0.725,
      "eps": 1.8,
      "source": {
        "quote": "akshare",
        "ohlcv": "yfinance",
        "fundamentals": "yfinance"
      },
      "confidence": {
        "quote": 0.95,
        "ohlcv": 0.85,
        "fundamentals": 0.8
      },
      "source_timestamp": "2026-05-18T07:54:57.873250",
      "last_verified_at": "2026-05-18T07:55:00.345128",
      "is_estimated": true,
      "estimated_fields": [
        "dividend_yield"
      ],
      "company_name": "Xiaomi",
      "symbol": "01810",
      "industry": "Consumer Electronics / EV / IoT",
      "sector": "Information Technology",
      "technical_rating": {
        "score": -3,
        "rating": "Sell",
        "color": "#F44336",
        "signals": [
          "Trend bearish",
          "MACD negative"
        ]
      },
      "derivative_analysis": {
        "daily_expected_move": 0.7079798989675021,
        "atr_percent": 3.7669957871986828,
        "support_level": 29.020000457763672,
        "resistance_level": 32.400001525878906,
        "tight_stop_loss": 28.946428538731166,
        "target_1r": 32.41357146126883,
        "target_2r": 34.14714292253767,
        "risk_reward_ratio": "1:2"
      },
      "expert_commentary": {
        "technical": "Xiaomi RSI 47.5, MACD -0.24, trend bearish.",
        "volatility": "Annualized volatility 36.6% with ATR 3.8%.",
        "derivative": "Expected daily move HK$0.71; support HK$29.02, resistance HK$32.40."
      },
      "stale": false
    },
    "meituan": {
      "price": 82.05,
      "open": 82.2,
      "high": 82.7,
      "low": 81.05,
      "volume": 36182404,
      "turnover": 2968766248.2,
      "change": -0.65,
      "change_pct": -0.78597,
      "amplitude": 2.010968921389404,
      "ma_5": 84.43999938964843,
      "ma_10": 84.09000015258789,
      "ma_20": 83.76499977111817,
      "ma_50": 82.66099960327148,
      "ma_200": 82.37155138213059,
      "ema_12": 83.96907129375766,
      "ema_26": 83.84126531657425,
      "rsi_14": 50.52357307114802,
      "rsi_6": 39.47366730325366,
      "macd": 0.1278059771834137,
      "macd_signal": 0.11502537946507232,
      "macd_histogram": 0.012780597718341363,
      "bb_upper": 87.02997906256542,
      "bb_middle": 83.76499977111817,
      "bb_lower": 80.50002047967092,
      "bb_width": 7.7955692720553165,
      "atr": 2.942856924874442,
      "volatility": 30.759215991258355,
      "historical_vol_20": 30.759215991258355,
      "historical_vol_60": 0.0,
      "momentum_10": -1.7953320708687173,
      "stoch_k": 16.59198072055687,
      "stoch_d": 16.59198072055687,
      "williams_r": -83.40801927944312,
      "52w_high": 90.0,
      "52w_low": 74.5,
      "52w_position": 48.709697108114916,
      "avg_volume_20": 35239460.8,
      "volume_ratio": 1.0270873384078567,
      "support_levels": [
        80.30000305175781
      ],
      "resistance_levels": [
        87.5999984741211
      ],
      "market_cap_billion": 594,
      "market_cap_display": "$594B",
      "market_cap_hkd": "HK$4635B",
      "pe_ratio": 15.4923525,
      "pb_ratio": 2.8846025,
      "ps_ratio": 1.3885201,
      "peg_ratio": 16.84,
      "ev_ebitda": -17.67,
      "fcf_yield": -2.809556965692191,
      "roe": -14.434,
      "roa": -5.778999600000001,
      "gross_margin": 30.425,
      "op_margin": -21.325001,
      "net_margin": -6.401,
      "revenue_growth": 2.8000000000000003,
      "earnings_growth": 57.2,
      "revenue_billion": 364.854738944,
      "debt_equity": 0.57368,
      "cash_billion": 166.833700864,
      "net_cash_billion": 80.214597632,
      "fcf_billion": -16.698223616,
      "dividend_yield": 0.0,
      "beta": 0.201,
      "eps": -4.52,
      "source": {
        "quote": "akshare",
        "ohlcv": "yfinance",
        "fundamentals": "yfinance"
      },
      "confidence": {
        "quote": 0.95,
        "ohlcv": 0.85,
        "fundamentals": 0.8
      },
      "source_timestamp": "2026-05-18T07:55:35.294237",
      "last_verified_at": "2026-05-18T07:55:36.593868",
      "is_estimated": true,
      "estimated_fields": [
        "earnings_growth",
        "dividend_yield"
      ],
      "company_name": "Meituan",
      "symbol": "03690",
      "industry": "Local Services",
      "sector": "Consumer Discretionary",
      "technical_rating": {
        "score": 1,
        "rating": "Hold",
        "color": "#FF9800",
        "signals": [
          "MACD positive"
        ]
      },
      "derivative_analysis": {
        "daily_expected_move": 1.589840575421297,
        "atr_percent": 3.586662918798832,
        "support_level": 80.30000305175781,
        "resistance_level": 87.5999984741211,
        "tight_stop_loss": 77.63571461268833,
        "target_1r": 86.46428538731166,
        "target_2r": 90.87857077462333,
        "risk_reward_ratio": "1:2"
      },
      "expert_commentary": {
        "technical": "Meituan RSI 50.5, MACD 0.13, trend bearish.",
        "volatility": "Annualized volatility 30.8% with ATR 3.6%.",
        "derivative": "Expected daily move HK$1.59; support HK$80.30, resistance HK$87.60."
      },
      "stale": false
    },
    "baidu": {
      "price": 134.6,
      "open": 135.3,
      "high": 137.3,
      "low": 133.9,
      "volume": 8024817,
      "turnover": 1080140368.2,
      "change": -1.2,
      "change_pct": -0.88365,
      "amplitude": 2.5260029717682064,
      "ma_5": 137.67999877929688,
      "ma_10": 136.87999954223633,
      "ma_20": 129.47999992370606,
      "ma_50": 120.59600021362304,
      "ma_200": 121.26724137931035,
      "ema_12": 134.12888799668218,
      "ema_26": 128.632222696116,
      "rsi_14": 58.62745655357707,
      "rsi_6": 19.42855349169355,
      "macd": 5.496665300566178,
      "macd_signal": 4.946998770509561,
      "macd_histogram": 0.5496665300566175,
      "bb_upper": 146.29565702519704,
      "bb_middle": 129.47999992370606,
      "bb_lower": 112.66434282221508,
      "bb_width": 25.974138262896712,
      "atr": 6.071428571428571,
      "volatility": 45.387953821885134,
      "historical_vol_20": 45.387953821885134,
      "historical_vol_60": 0.0,
      "momentum_10": 7.256777004299413,
      "stoch_k": 57.72872180914382,
      "stoch_d": 57.72872180914382,
      "williams_r": -42.27127819085618,
      "52w_high": 145.1999969482422,
      "52w_low": 105.5999984741211,
      "52w_position": 72.97980464510695,
      "avg_volume_20": 12942590.55,
      "volume_ratio": 0.6277002249754396,
      "support_levels": [
        118.69999694824219
      ],
      "resistance_levels": [
        145.1999969482422
      ],
      "market_cap_billion": 60,
      "market_cap_display": "$60B",
      "market_cap_hkd": "HK$468B",
      "pe_ratio": 14.839885,
      "pb_ratio": 1.2190309,
      "ps_ratio": 2.8363397,
      "peg_ratio": 0.79,
      "ev_ebitda": 15.205,
      "fcf_yield": 27.709800711174875,
      "roe": 1.9040000000000001,
      "roa": 1.4780000999999998,
      "gross_margin": 43.882,
      "op_margin": 4.5300003,
      "net_margin": 4.33,
      "revenue_growth": -4.1000000000000005,
      "earnings_growth": -81.0,
      "revenue_billion": 129.079001088,
      "debt_equity": 0.33506,
      "cash_billion": 115.267002368,
      "net_cash_billion": 18.190000128,
      "fcf_billion": 16.640374784,
      "dividend_yield": 0.6,
      "beta": 0.524,
      "eps": 1.7,
      "source": {
        "quote": "akshare",
        "ohlcv": "yfinance",
        "fundamentals": "yfinance"
      },
      "confidence": {
        "quote": 0.95,
        "ohlcv": 0.85,
        "fundamentals": 0.8
      },
      "source_timestamp": "2026-05-18T07:53:11.208061",
      "last_verified_at": "2026-05-18T07:53:12.718633",
      "is_estimated": true,
      "estimated_fields": [
        "dividend_yield"
      ],
      "company_name": "Baidu",
      "symbol": "09888",
      "industry": "Technology / Search / AI",
      "sector": "Communication Services",
      "technical_rating": {
        "score": 3,
        "rating": "Buy",
        "color": "#4CAF50",
        "signals": [
          "Trend bullish",
          "MACD positive"
        ]
      },
      "derivative_analysis": {
        "daily_expected_move": 3.8484459712677523,
        "atr_percent": 4.510719592443218,
        "support_level": 118.69999694824219,
        "resistance_level": 145.1999969482422,
        "tight_stop_loss": 125.49285714285713,
        "target_1r": 143.70714285714286,
        "target_2r": 152.81428571428572,
        "risk_reward_ratio": "1:2"
      },
      "expert_commentary": {
        "technical": "Baidu RSI 58.6, MACD 5.50, trend bullish.",
        "volatility": "Annualized volatility 45.4% with ATR 4.5%.",
        "derivative": "Expected daily move HK$3.85; support HK$118.70, resistance HK$145.20."
      },
      "stale": false
    },
    "jd": {
      "price": 126.1,
      "open": 124.3,
      "high": 127.0,
      "low": 123.5,
      "volume": 7012041,
      "turnover": 884218370.0999999,
      "change": -1.8,
      "change_pct": -1.40735,
      "amplitude": 2.7755749405233945,
      "ma_5": 126.16000061035156,
      "ma_10": 121.94000015258788,
      "ma_20": 120.25500030517578,
      "ma_50": 114.52234893798828,
      "ma_200": 113.04980508212385,
      "ema_12": 122.72989296503786,
      "ema_26": 119.51094756293315,
      "rsi_14": 68.25395335656866,
      "rsi_6": 74.52226420815694,
      "macd": 3.2189454021047084,
      "macd_signal": 2.8970508618942374,
      "macd_histogram": 0.3218945402104709,
      "bb_upper": 129.0216359991935,
      "bb_middle": 120.25500030517578,
      "bb_lower": 111.48836461115808,
      "bb_width": 14.580076789772207,
      "atr": 3.4142864772251675,
      "volatility": 35.63365568331618,
      "historical_vol_20": 35.63365568331618,
      "historical_vol_60": 0.0,
      "momentum_10": 8.605852205361245,
      "stoch_k": 65.57375955654464,
      "stoch_d": 65.57375955654464,
      "williams_r": -34.426240443455356,
      "52w_high": 130.10000610351562,
      "52w_low": 96.51679992675781,
      "52w_position": 88.38702554262807,
      "avg_volume_20": 9806136.05,
      "volume_ratio": 0.7156173404304338,
      "support_levels": [
        115.30000305175781
      ],
      "resistance_levels": [
        130.10000610351562
      ],
      "market_cap_billion": 208,
      "market_cap_display": "$208B",
      "market_cap_hkd": "HK$1624B",
      "pe_ratio": 7.6778517,
      "pb_ratio": 1.3902919,
      "ps_ratio": 0.26043203,
      "peg_ratio": 1.05,
      "ev_ebitda": 45.308,
      "fcf_yield": 3.3645427418838443,
      "roe": 6.0040000000000004,
      "roa": -0.27799999999999997,
      "gross_margin": 9.32,
      "op_margin": 1.206,
      "net_margin": 1.04600005,
      "revenue_growth": 4.9,
      "earnings_growth": -50.7,
      "revenue_billion": 1323.697045504,
      "debt_equity": 0.38478,
      "cash_billion": 202.132996096,
      "net_cash_billion": 94.112997376,
      "fcf_billion": 7.0058752,
      "dividend_yield": 306.0,
      "beta": 0.403,
      "eps": 5.33,
      "source": {
        "quote": "akshare",
        "ohlcv": "yfinance",
        "fundamentals": "yfinance"
      },
      "confidence": {
        "quote": 0.95,
        "ohlcv": 0.85,
        "fundamentals": 0.8
      },
      "source_timestamp": "2026-05-18T07:53:46.300615",
      "last_verified_at": "2026-05-18T07:53:47.699744",
      "is_estimated": false,
      "estimated_fields": [],
      "company_name": "JD.com",
      "symbol": "09618",
      "industry": "E-commerce / Logistics",
      "sector": "Consumer Discretionary",
      "technical_rating": {
        "score": 3,
        "rating": "Buy",
        "color": "#4CAF50",
        "signals": [
          "Trend bullish",
          "MACD positive"
        ]
      },
      "derivative_analysis": {
        "daily_expected_move": 2.830578446580028,
        "atr_percent": 2.7076022817011642,
        "support_level": 115.30000305175781,
        "resistance_level": 130.10000610351562,
        "tight_stop_loss": 120.97857028416225,
        "target_1r": 131.22142971583776,
        "target_2r": 136.3428594316755,
        "risk_reward_ratio": "1:2"
      },
      "expert_commentary": {
        "technical": "JD.com RSI 68.3, MACD 3.22, trend bullish.",
        "volatility": "Annualized volatility 35.6% with ATR 2.7%.",
        "derivative": "Expected daily move HK$2.83; support HK$115.30, resistance HK$130.10."
      },
      "stale": false
    }
  },
  "schema_version": "v1"
}