{
  "timestamp": "2026-06-08T02:30:33.376155",
  "companies": {
    "tencent": {
      "price": 448.6,
      "open": 447.8,
      "high": 452.0,
      "low": 444.8,
      "volume": 9952101,
      "turnover": 4874473472.0,
      "change": -4.6,
      "change_pct": -1.015,
      "amplitude": 1.604993312527862,
      "ma_5": 462.36,
      "ma_10": 447.34,
      "ma_20": 449.89000000000004,
      "ma_50": 472.39799999999997,
      "ma_200": 484.55303030303025,
      "ema_12": 452.1671973665809,
      "ema_26": 457.4495055020347,
      "rsi_14": 50.87463556851314,
      "rsi_6": 64.45497630331755,
      "macd": -5.282308135453775,
      "macd_signal": -4.754077321908397,
      "macd_histogram": -0.5282308135453775,
      "bb_upper": 476.6989462679905,
      "bb_middle": 449.89000000000004,
      "bb_lower": 423.0810537320096,
      "bb_width": 11.91800051923379,
      "atr": 16.22857142857142,
      "volatility": 46.17068390702473,
      "historical_vol_20": 46.17068390702473,
      "historical_vol_60": 38.23692806890959,
      "momentum_10": 2.8701594533029664,
      "stoch_k": 48.44720496894414,
      "stoch_d": 48.44720496894414,
      "williams_r": -51.55279503105586,
      "52w_high": 553.2,
      "52w_low": 425.0,
      "52w_position": 20.74882995319814,
      "avg_volume_20": 35202864.1,
      "volume_ratio": 0.30810615207868836,
      "support_levels": [
        425.0
      ],
      "resistance_levels": [
        481.6
      ],
      "market_cap_billion": 537,
      "market_cap_display": "$537B",
      "market_cap_hkd": "HK$4194B",
      "pe_ratio": 11.695854,
      "pb_ratio": 3.1033876,
      "ps_ratio": 5.270505,
      "peg_ratio": 1.35,
      "ev_ebitda": 14.604,
      "fcf_yield": 24.191141952837228,
      "roe": 20.515,
      "roa": 7.9169996000000005,
      "gross_margin": 56.449000000000005,
      "op_margin": 34.294999999999995,
      "net_margin": 30.606002,
      "revenue_growth": 9.1,
      "earnings_growth": 22.900000000000002,
      "revenue_billion": 768.201981952,
      "debt_equity": 0.33468000000000003,
      "cash_billion": 459.714985984,
      "net_cash_billion": 54.203973632,
      "fcf_billion": 130.08662528,
      "dividend_yield": 117.0,
      "beta": 0.741,
      "eps": 27.96,
      "source": {
        "quote": "akshare",
        "ohlcv": "akshare",
        "fundamentals": "yfinance"
      },
      "confidence": {
        "quote": 0.95,
        "ohlcv": 0.95,
        "fundamentals": 0.8
      },
      "source_timestamp": "2026-06-08T02:27:15.183384",
      "last_verified_at": "2026-06-08T02:27:18.634815",
      "is_estimated": false,
      "estimated_fields": [],
      "company_name": "Tencent",
      "symbol": "00700",
      "industry": "Technology / Gaming / Social Media",
      "sector": "Communication Services",
      "technical_rating": {
        "score": -3,
        "rating": "Sell",
        "color": "#F44336",
        "signals": [
          "Trend bearish",
          "MACD negative"
        ]
      },
      "derivative_analysis": {
        "daily_expected_move": 13.047439942719071,
        "atr_percent": 3.617603974269153,
        "support_level": 425.0,
        "resistance_level": 481.6,
        "tight_stop_loss": 424.25714285714287,
        "target_1r": 472.9428571428572,
        "target_2r": 497.2857142857143,
        "risk_reward_ratio": "1:2"
      },
      "expert_commentary": {
        "technical": "Tencent RSI 50.9, MACD -5.28, trend bearish.",
        "volatility": "Annualized volatility 46.2% with ATR 3.6%.",
        "derivative": "Expected daily move HK$13.05; support HK$425.00, resistance HK$481.60."
      },
      "stale": false
    },
    "alibaba": {
      "price": 119.1,
      "open": 118.3,
      "high": 119.2,
      "low": 117.8,
      "volume": 31456480,
      "turnover": 4165287840.0,
      "change": -3.3,
      "change_pct": -2.69608,
      "amplitude": 1.1754827875734726,
      "ma_5": 124.53999999999999,
      "ma_10": 124.00999999999999,
      "ma_20": 128.01000000000002,
      "ma_50": 128.386,
      "ma_200": 129.06969696969693,
      "ema_12": 124.97323300045244,
      "ema_26": 127.32330071589863,
      "rsi_14": 34.02061855670105,
      "rsi_6": 46.296296296296276,
      "macd": -2.350067715446187,
      "macd_signal": -2.115060943901568,
      "macd_histogram": -0.2350067715446187,
      "bb_upper": 138.32346692436644,
      "bb_middle": 128.01000000000002,
      "bb_lower": 117.6965330756336,
      "bb_width": 16.11353319954132,
      "atr": 4.592857142857144,
      "volatility": 41.56608838541142,
      "historical_vol_20": 41.56608838541142,
      "historical_vol_60": 46.49668814045063,
      "momentum_10": -6.504702194357365,
      "stoch_k": 8.47457627118644,
      "stoch_d": 8.47457627118644,
      "williams_r": -91.52542372881356,
      "52w_high": 140.9,
      "52w_low": 118.5,
      "52w_position": 3.571428571428558,
      "avg_volume_20": 88214825.35,
      "volume_ratio": 0.39642099682511023,
      "support_levels": [
        119.3
      ],
      "resistance_levels": [
        137.9
      ],
      "market_cap_billion": 358,
      "market_cap_display": "$358B",
      "market_cap_hkd": "HK$2798B",
      "pe_ratio": 12.226398,
      "pb_ratio": 1.8021214,
      "ps_ratio": 2.2311637,
      "peg_ratio": 0.44,
      "ev_ebitda": 21.031,
      "fcf_yield": -12.282871603408543,
      "roe": 9.2159994,
      "roa": 2.12,
      "gross_margin": 39.811,
      "op_margin": 1.01499995,
      "net_margin": 10.12,
      "revenue_growth": 2.9000000000000004,
      "earnings_growth": 104.1,
      "revenue_billion": 1023.67002624,
      "debt_equity": 0.25014,
      "cash_billion": 316.819996672,
      "net_cash_billion": 35.098001408,
      "fcf_billion": -44.07425024,
      "dividend_yield": 84.0,
      "beta": 0.46,
      "eps": 6.36,
      "source": {
        "quote": "akshare",
        "ohlcv": "akshare",
        "fundamentals": "yfinance"
      },
      "confidence": {
        "quote": 0.95,
        "ohlcv": 0.95,
        "fundamentals": 0.8
      },
      "source_timestamp": "2026-06-08T02:27:54.698323",
      "last_verified_at": "2026-06-08T02:27:58.400213",
      "is_estimated": false,
      "estimated_fields": [],
      "company_name": "Alibaba",
      "symbol": "09988",
      "industry": "E-commerce / Cloud",
      "sector": "Consumer Discretionary",
      "technical_rating": {
        "score": -3,
        "rating": "Sell",
        "color": "#F44336",
        "signals": [
          "Trend bearish",
          "MACD negative"
        ]
      },
      "derivative_analysis": {
        "daily_expected_move": 3.118535181291927,
        "atr_percent": 3.8563032265803057,
        "support_level": 119.3,
        "resistance_level": 137.9,
        "tight_stop_loss": 112.21071428571427,
        "target_1r": 125.98928571428571,
        "target_2r": 132.87857142857143,
        "risk_reward_ratio": "1:2"
      },
      "expert_commentary": {
        "technical": "Alibaba RSI 34.0, MACD -2.35, trend bearish.",
        "volatility": "Annualized volatility 41.6% with ATR 3.9%.",
        "derivative": "Expected daily move HK$3.12; support HK$119.30, resistance HK$137.90."
      },
      "stale": false
    },
    "xiaomi": {
      "price": 27.36,
      "open": 27.34,
      "high": 27.42,
      "low": 26.98,
      "volume": 40871784,
      "turnover": 1332623376.0,
      "change": -0.44,
      "change_pct": -1.58273,
      "amplitude": 1.6081871345029288,
      "ma_5": 28.387999999999998,
      "ma_10": 28.542,
      "ma_20": 29.695,
      "ma_50": 30.7448,
      "ma_200": 31.426060606060606,
      "ema_12": 28.77614744643575,
      "ema_26": 29.636809084223515,
      "rsi_14": 28.650137741046834,
      "rsi_6": 43.40659340659341,
      "macd": -0.8606616377877643,
      "macd_signal": -0.7745954740089879,
      "macd_histogram": -0.0860661637787764,
      "bb_upper": 32.39980683228951,
      "bb_middle": 29.695,
      "bb_lower": 26.99019316771049,
      "bb_width": 18.217254300653362,
      "atr": 1.062857142857143,
      "volatility": 29.92912664243159,
      "historical_vol_20": 29.92912664243159,
      "historical_vol_60": 40.98710504950092,
      "momentum_10": -7.392473118279579,
      "stoch_k": 14.215686274509768,
      "stoch_d": 14.215686274509768,
      "williams_r": -85.78431372549024,
      "52w_high": 36.32,
      "52w_low": 27.56,
      "52w_position": 0.0,
      "avg_volume_20": 142741297.3,
      "volume_ratio": 0.3427141263623642,
      "support_levels": [
        27.56
      ],
      "resistance_levels": [
        31.8
      ],
      "market_cap_billion": 85,
      "market_cap_display": "$85B",
      "market_cap_hkd": "HK$664B",
      "pe_ratio": 15.508337,
      "pb_ratio": 2.290885,
      "ps_ratio": 1.5846603,
      "peg_ratio": 2.31,
      "ev_ebitda": 19.407,
      "fcf_yield": 9.112609896758357,
      "roe": 13.996,
      "roa": 3.519,
      "gross_margin": 22.062999,
      "op_margin": 4.459,
      "net_margin": 7.9619995999999995,
      "revenue_growth": -10.9,
      "earnings_growth": -58.099999999999994,
      "revenue_billion": 445.134962688,
      "debt_equity": 0.13294,
      "cash_billion": 98.225414144,
      "net_cash_billion": 62.85817856,
      "fcf_billion": 7.767308288,
      "dividend_yield": 0.1,
      "beta": 0.684,
      "eps": 1.81,
      "source": {
        "quote": "akshare",
        "ohlcv": "akshare",
        "fundamentals": "yfinance"
      },
      "confidence": {
        "quote": 0.95,
        "ohlcv": 0.95,
        "fundamentals": 0.8
      },
      "source_timestamp": "2026-06-08T02:28:34.564332",
      "last_verified_at": "2026-06-08T02:28:36.689276",
      "is_estimated": true,
      "estimated_fields": [
        "dividend_yield"
      ],
      "company_name": "Xiaomi",
      "symbol": "01810",
      "industry": "Consumer Electronics / EV / IoT",
      "sector": "Information Technology",
      "technical_rating": {
        "score": -1,
        "rating": "Hold",
        "color": "#FF9800",
        "signals": [
          "RSI oversold",
          "Trend bearish",
          "MACD negative"
        ]
      },
      "derivative_analysis": {
        "daily_expected_move": 0.5158338840039084,
        "atr_percent": 3.884711779448622,
        "support_level": 27.56,
        "resistance_level": 31.8,
        "tight_stop_loss": 25.765714285714285,
        "target_1r": 28.954285714285714,
        "target_2r": 30.548571428571428,
        "risk_reward_ratio": "1:2"
      },
      "expert_commentary": {
        "technical": "Xiaomi RSI 28.7, MACD -0.86, trend bearish.",
        "volatility": "Annualized volatility 29.9% with ATR 3.9%.",
        "derivative": "Expected daily move HK$0.52; support HK$27.56, resistance HK$31.80."
      },
      "stale": false
    },
    "meituan": {
      "price": 76.8,
      "open": 77.3,
      "high": 77.75,
      "low": 76.05,
      "volume": 19626876,
      "turnover": 1661184896.0,
      "change": -3.15,
      "change_pct": -3.93996,
      "amplitude": 2.2135416666666705,
      "ma_5": 80.25,
      "ma_10": 78.275,
      "ma_20": 80.9375,
      "ma_50": 83.113,
      "ma_200": 81.79242424242425,
      "ema_12": 79.47363033908164,
      "ema_26": 80.74044441219466,
      "rsi_14": 42.1897810218978,
      "rsi_6": 57.142857142857125,
      "macd": -1.266814073113025,
      "macd_signal": -1.1401326658017226,
      "macd_histogram": -0.1266814073113025,
      "bb_upper": 88.48182733913369,
      "bb_middle": 80.9375,
      "bb_lower": 73.39317266086631,
      "bb_width": 18.642353270446176,
      "atr": 3.9571428571428564,
      "volatility": 59.31501487948658,
      "historical_vol_20": 59.31501487948658,
      "historical_vol_60": 54.72966483408472,
      "momentum_10": -2.5380710659898478,
      "stoch_k": 31.164383561643827,
      "stoch_d": 31.164383561643827,
      "williams_r": -68.83561643835617,
      "52w_high": 90.0,
      "52w_low": 73.3,
      "52w_position": 20.958083832335326,
      "avg_volume_20": 54549707.35,
      "volume_ratio": 0.39527949914840377,
      "support_levels": [
        73.3
      ],
      "resistance_levels": [
        87.6
      ],
      "market_cap_billion": 556,
      "market_cap_display": "$556B",
      "market_cap_hkd": "HK$4339B",
      "pe_ratio": 16.15373,
      "pb_ratio": 2.6883004,
      "ps_ratio": 1.2851902,
      "peg_ratio": 30.12,
      "ev_ebitda": -10.507,
      "fcf_yield": -5.533223730973451,
      "roe": -24.093999999999998,
      "roa": -8.501001,
      "gross_margin": 28.38,
      "op_margin": -7.538,
      "net_margin": -10.885,
      "revenue_growth": 5.6000000000000005,
      "earnings_growth": 57.2,
      "revenue_billion": 369.687494656,
      "debt_equity": 0.75262,
      "cash_billion": 180.370161664,
      "net_cash_billion": 67.566280704,
      "fcf_billion": -30.781749248,
      "dividend_yield": 0.0,
      "beta": 0.184,
      "eps": -4.54,
      "source": {
        "quote": "akshare",
        "ohlcv": "akshare",
        "fundamentals": "yfinance"
      },
      "confidence": {
        "quote": 0.95,
        "ohlcv": 0.95,
        "fundamentals": 0.8
      },
      "source_timestamp": "2026-06-08T02:29:12.000129",
      "last_verified_at": "2026-06-08T02:29:13.595425",
      "is_estimated": true,
      "estimated_fields": [
        "earnings_growth",
        "dividend_yield"
      ],
      "company_name": "Meituan",
      "symbol": "03690",
      "industry": "Local Services",
      "sector": "Consumer Discretionary",
      "technical_rating": {
        "score": -3,
        "rating": "Sell",
        "color": "#F44336",
        "signals": [
          "Trend bearish",
          "MACD negative"
        ]
      },
      "derivative_analysis": {
        "daily_expected_move": 2.869627947578831,
        "atr_percent": 5.152529761904761,
        "support_level": 73.3,
        "resistance_level": 87.6,
        "tight_stop_loss": 70.86428571428571,
        "target_1r": 82.73571428571428,
        "target_2r": 88.67142857142856,
        "risk_reward_ratio": "1:2"
      },
      "expert_commentary": {
        "technical": "Meituan RSI 42.2, MACD -1.27, trend bearish.",
        "volatility": "Annualized volatility 59.3% with ATR 5.2%.",
        "derivative": "Expected daily move HK$2.87; support HK$73.30, resistance HK$87.60."
      },
      "stale": false
    },
    "baidu": {
      "price": 128.2,
      "open": 128.5,
      "high": 129.6,
      "low": 127.1,
      "volume": 8435893,
      "turnover": 1081481482.6,
      "change": 1.7,
      "change_pct": 1.34387,
      "amplitude": 1.9500780031201248,
      "ma_5": 132.05999755859375,
      "ma_10": 135.50999755859374,
      "ma_20": 131.3199993133545,
      "ma_50": 121.75599990844727,
      "ma_200": 121.80819652119621,
      "ema_12": 132.47253267689362,
      "ema_26": 129.33125291826926,
      "rsi_14": 55.03731003368322,
      "rsi_6": 18.407953400699768,
      "macd": 3.141279758624364,
      "macd_signal": 2.827151782761928,
      "macd_histogram": 0.31412797586243624,
      "bb_upper": 146.90070258819475,
      "bb_middle": 131.3199993133545,
      "bb_lower": 115.73929603851421,
      "bb_width": 23.729368498794685,
      "atr": 5.907141549246652,
      "volatility": 49.86756808930353,
      "historical_vol_20": 49.86756808930353,
      "historical_vol_60": 43.79677879431496,
      "momentum_10": -9.013482965494342,
      "stoch_k": 20.5645137721364,
      "stoch_d": 20.5645137721364,
      "williams_r": -79.4354862278636,
      "52w_high": 145.1999969482422,
      "52w_low": 105.5999984741211,
      "52w_position": 57.0707054165428,
      "avg_volume_20": 13770344.95,
      "volume_ratio": 0.6126203105754443,
      "support_levels": [
        118.69999694824219
      ],
      "resistance_levels": [
        145.1999969482422
      ],
      "market_cap_billion": 57,
      "market_cap_display": "$57B",
      "market_cap_hkd": "HK$446B",
      "pe_ratio": 14.484476,
      "pb_ratio": 1.1287605,
      "ps_ratio": 2.7114043,
      "peg_ratio": 0.78,
      "ev_ebitda": 14.624,
      "fcf_yield": 13.914428154284794,
      "roe": 0.319,
      "roa": 1.2519999,
      "gross_margin": 42.084998,
      "op_margin": 9.955,
      "net_margin": 1.023,
      "revenue_growth": -1.2,
      "earnings_growth": -59.3,
      "revenue_billion": 128.701997056,
      "debt_equity": 0.322,
      "cash_billion": 116.890001408,
      "net_cash_billion": 22.754000896,
      "fcf_billion": 7.958624768,
      "dividend_yield": 0.6,
      "beta": 0.524,
      "eps": -0.15,
      "source": {
        "quote": "akshare",
        "ohlcv": "yfinance",
        "fundamentals": "yfinance"
      },
      "confidence": {
        "quote": 0.95,
        "ohlcv": 0.85,
        "fundamentals": 0.8
      },
      "source_timestamp": "2026-05-22T09:48:23.454256",
      "last_verified_at": "2026-05-22T09:48:24.317140",
      "is_estimated": true,
      "estimated_fields": [
        "dividend_yield"
      ],
      "company_name": "Baidu",
      "symbol": "09888",
      "industry": "Technology / Search / AI",
      "sector": "Communication Services",
      "technical_rating": {
        "score": 1,
        "rating": "Hold",
        "color": "#FF9800",
        "signals": [
          "MACD positive"
        ]
      },
      "derivative_analysis": {
        "daily_expected_move": 4.027225462897786,
        "atr_percent": 4.607754718601133,
        "support_level": 118.69999694824219,
        "resistance_level": 145.1999969482422,
        "tight_stop_loss": 119.33928767613001,
        "target_1r": 137.06071232386998,
        "target_2r": 145.92142464773994,
        "risk_reward_ratio": "1:2"
      },
      "expert_commentary": {
        "technical": "Baidu RSI 55.0, MACD 3.14, trend bearish.",
        "volatility": "Annualized volatility 49.9% with ATR 4.6%.",
        "derivative": "Expected daily move HK$4.03; support HK$118.70, resistance HK$145.20."
      },
      "stale": false
    },
    "jd": {
      "price": 121.7,
      "open": 123.5,
      "high": 123.5,
      "low": 121.1,
      "volume": 8256004,
      "turnover": 1004755686.8000001,
      "change": -1.8,
      "change_pct": -1.45749,
      "amplitude": 1.9720624486442118,
      "ma_5": 125.08000030517579,
      "ma_10": 124.85000076293946,
      "ma_20": 121.00000076293945,
      "ma_50": 116.4017253112793,
      "ma_200": 113.97954922035092,
      "ema_12": 123.55755779072652,
      "ema_26": 120.8988150192503,
      "rsi_14": 58.78134338480116,
      "rsi_6": 15.57376741626436,
      "macd": 2.658742771476213,
      "macd_signal": 2.392868494328592,
      "macd_histogram": 0.265874277147621,
      "bb_upper": 130.62995464230823,
      "bb_middle": 121.00000076293945,
      "bb_lower": 111.37004688357067,
      "bb_width": 15.91727903908956,
      "atr": 3.5928589957101003,
      "volatility": 37.18087695841784,
      "historical_vol_20": 37.18087695841784,
      "historical_vol_60": 37.4630938344859,
      "momentum_10": 2.7004193656052213,
      "stoch_k": 40.9835997228404,
      "stoch_d": 40.9835997228404,
      "williams_r": -59.0164002771596,
      "52w_high": 130.10000610351562,
      "52w_low": 96.51679992675781,
      "52w_position": 74.98747108581045,
      "avg_volume_20": 10822665.65,
      "volume_ratio": 0.7633520490397853,
      "support_levels": [
        115.30000305175781
      ],
      "resistance_levels": [
        130.10000610351562
      ],
      "market_cap_billion": 200,
      "market_cap_display": "$200B",
      "market_cap_hkd": "HK$1567B",
      "pe_ratio": 7.404077,
      "pb_ratio": 1.339394,
      "ps_ratio": 0.25114563,
      "peg_ratio": 1.05,
      "ev_ebitda": 43.604,
      "fcf_yield": 3.4861860291828495,
      "roe": 6.0040000000000004,
      "roa": -0.27799999999999997,
      "gross_margin": 9.32,
      "op_margin": 1.206,
      "net_margin": 1.04600005,
      "revenue_growth": 4.9,
      "earnings_growth": -50.7,
      "revenue_billion": 1323.697045504,
      "debt_equity": 0.38478,
      "cash_billion": 202.132996096,
      "net_cash_billion": 94.112997376,
      "fcf_billion": 7.0058752,
      "dividend_yield": 317.0,
      "beta": 0.403,
      "eps": 5.32,
      "source": {
        "quote": "akshare",
        "ohlcv": "yfinance",
        "fundamentals": "yfinance"
      },
      "confidence": {
        "quote": 0.95,
        "ohlcv": 0.85,
        "fundamentals": 0.8
      },
      "source_timestamp": "2026-05-22T09:49:09.633906",
      "last_verified_at": "2026-05-22T09:49:10.990736",
      "is_estimated": false,
      "estimated_fields": [],
      "company_name": "JD.com",
      "symbol": "09618",
      "industry": "E-commerce / Logistics",
      "sector": "Consumer Discretionary",
      "technical_rating": {
        "score": 3,
        "rating": "Buy",
        "color": "#4CAF50",
        "signals": [
          "Trend bullish",
          "MACD positive"
        ]
      },
      "derivative_analysis": {
        "daily_expected_move": 2.8504270897244233,
        "atr_percent": 2.952225961963928,
        "support_level": 115.30000305175781,
        "resistance_level": 130.10000610351562,
        "tight_stop_loss": 116.31071150643486,
        "target_1r": 127.08928849356515,
        "target_2r": 132.4785769871303,
        "risk_reward_ratio": "1:2"
      },
      "expert_commentary": {
        "technical": "JD.com RSI 58.8, MACD 2.66, trend bullish.",
        "volatility": "Annualized volatility 37.2% with ATR 3.0%.",
        "derivative": "Expected daily move HK$2.85; support HK$115.30, resistance HK$130.10."
      },
      "stale": false
    },
    "hsbc": {
      "price": 141.0,
      "open": 140.6,
      "high": 141.3,
      "low": 139.4,
      "volume": 7056114,
      "turnover": 1027171152.0,
      "change": -0.8,
      "change_pct": -0.56418,
      "amplitude": 1.3475177304964578,
      "ma_5": 144.76,
      "ma_10": 145.26,
      "ma_20": 142.68740000000003,
      "ma_50": 138.70056,
      "ma_200": 135.82272727272726,
      "ema_12": 143.8864772278041,
      "ema_26": 142.25477182192515,
      "rsi_14": 58.0952380952381,
      "rsi_6": 26.92307692307692,
      "macd": 1.6317054058789608,
      "macd_signal": 1.4685348652910648,
      "macd_histogram": 0.16317054058789604,
      "bb_upper": 148.98343673432743,
      "bb_middle": 142.68740000000003,
      "bb_lower": 136.39136326567262,
      "bb_width": 8.824937218461336,
      "atr": 2.8428571428571496,
      "volatility": 20.87349993248292,
      "historical_vol_20": 20.87349993248292,
      "historical_vol_60": 32.63322051194766,
      "momentum_10": -2.7491408934707904,
      "stoch_k": 31.77570093457944,
      "stoch_d": 31.77570093457944,
      "williams_r": -68.22429906542055,
      "52w_high": 147.2,
      "52w_low": 118.116,
      "52w_position": 80.40159537890253,
      "avg_volume_20": 13640224.05,
      "volume_ratio": 0.5336183609095482,
      "support_levels": [
        137.816
      ],
      "resistance_levels": [
        147.2
      ],
      "market_cap_billion": 325,
      "market_cap_display": "$325B",
      "market_cap_hkd": "HK$2538B",
      "pe_ratio": 9.7087145,
      "pb_ratio": 1.7708168,
      "ps_ratio": 37.940422,
      "peg_ratio": 0.91,
      "ev_ebitda": 12.0,
      "fcf_yield": 0.0,
      "roe": 11.611,
      "roa": 0.722,
      "gross_margin": 0.0,
      "op_margin": 50.684,
      "net_margin": 34.977000000000004,
      "revenue_growth": 3.3000000000000003,
      "earnings_growth": 2.6,
      "revenue_billion": 63.773999104,
      "debt_equity": 0.0,
      "cash_billion": 1162.82097664,
      "net_cash_billion": 389.367988224,
      "fcf_billion": 0.0,
      "dividend_yield": 413.0,
      "beta": 0.579,
      "eps": 9.49,
      "source": {
        "quote": "akshare",
        "ohlcv": "akshare",
        "fundamentals": "yfinance"
      },
      "confidence": {
        "quote": 0.95,
        "ohlcv": 0.95,
        "fundamentals": 0.8
      },
      "source_timestamp": "2026-06-08T02:29:50.997003",
      "last_verified_at": "2026-06-08T02:29:53.504941",
      "is_estimated": true,
      "estimated_fields": [
        "debt_equity",
        "ev_ebitda"
      ],
      "company_name": "HSBC",
      "symbol": "00005",
      "industry": "Banking / Financial Services",
      "sector": "Financials",
      "technical_rating": {
        "score": 1,
        "rating": "Hold",
        "color": "#FF9800",
        "signals": [
          "MACD positive"
        ]
      },
      "derivative_analysis": {
        "daily_expected_move": 1.854018729432176,
        "atr_percent": 2.0162107396149995,
        "support_level": 137.816,
        "resistance_level": 147.2,
        "tight_stop_loss": 136.73571428571427,
        "target_1r": 145.26428571428573,
        "target_2r": 149.52857142857144,
        "risk_reward_ratio": "1:2"
      },
      "expert_commentary": {
        "technical": "HSBC RSI 58.1, MACD 1.63, trend bearish.",
        "volatility": "Annualized volatility 20.9% with ATR 2.0%.",
        "derivative": "Expected daily move HK$1.85; support HK$137.82, resistance HK$147.20."
      },
      "stale": false
    },
    "hk3033": {
      "price": 4.691999912261963,
      "open": 4.699999809265137,
      "high": 4.699999809265137,
      "low": 4.625999927520752,
      "volume": 646550834,
      "turnover": 4008564000.0,
      "change": -0.09399986267089844,
      "change_pct": -1.9640590700240281,
      "amplitude": 1.5771501092955096,
      "ma_5": 4.8793999999999995,
      "ma_10": 4.847099999999999,
      "ma_20": 4.845250000000001,
      "ma_50": 4.8137799999999995,
      "ma_200": 4.823318181818182,
      "ema_12": 4.834075756680001,
      "ema_26": 4.83824662001809,
      "rsi_14": 48.144712430426715,
      "rsi_6": 43.80281690140844,
      "macd": -0.004170863338089248,
      "macd_signal": -0.0037537770042803233,
      "macd_histogram": -0.0004170863338089246,
      "bb_upper": 5.067175099977448,
      "bb_middle": 4.845250000000001,
      "bb_lower": 4.623324900022554,
      "bb_width": 9.160522159948293,
      "atr": 0.12399999999999992,
      "volatility": 29.204685006634172,
      "historical_vol_20": 29.204685006634172,
      "historical_vol_60": 30.68428446054418,
      "momentum_10": -2.975206611570251,
      "stoch_k": 14.925373134328249,
      "stoch_d": 14.925373134328249,
      "williams_r": -85.07462686567176,
      "52w_high": 5.095,
      "52w_low": 4.55,
      "52w_position": 26.788990825688057,
      "avg_volume_20": 2074069804.0,
      "volume_ratio": 0.41358426719566665,
      "support_levels": [
        4.668
      ],
      "resistance_levels": [
        5.095
      ],
      "market_cap_billion": 0,
      "market_cap_display": "$N/A",
      "market_cap_hkd": "HK$0B",
      "pe_ratio": 19.312847,
      "pb_ratio": 2.0,
      "ps_ratio": 0.0,
      "peg_ratio": 1.2,
      "ev_ebitda": 12.0,
      "fcf_yield": 0.0,
      "roe": 0.0,
      "roa": 0.0,
      "gross_margin": 0.0,
      "op_margin": 0.0,
      "net_margin": 0.0,
      "revenue_growth": 0.0,
      "earnings_growth": 0.0,
      "revenue_billion": 0.0,
      "debt_equity": 0.0,
      "cash_billion": 0.0,
      "net_cash_billion": 0.0,
      "fcf_billion": 0.0,
      "dividend_yield": 0.0,
      "beta": 1.0,
      "eps": 0.0,
      "source": {
        "quote": "yfinance",
        "ohlcv": "akshare",
        "fundamentals": "yfinance"
      },
      "confidence": {
        "quote": 0.85,
        "ohlcv": 0.95,
        "fundamentals": 0.8
      },
      "source_timestamp": "2026-06-08T02:30:29.104634",
      "last_verified_at": "2026-06-08T02:30:30.359047",
      "is_estimated": true,
      "estimated_fields": [
        "roe",
        "roa",
        "gross_margin",
        "op_margin",
        "net_margin",
        "revenue_growth",
        "earnings_growth",
        "revenue_billion",
        "debt_equity",
        "beta",
        "eps",
        "pb_ratio",
        "ps_ratio",
        "peg_ratio",
        "ev_ebitda"
      ],
      "company_name": "CSOP HS TECH",
      "symbol": "03033",
      "industry": "ETF / Hang Seng TECH",
      "sector": "ETF",
      "technical_rating": {
        "score": -1,
        "rating": "Hold",
        "color": "#FF9800",
        "signals": [
          "MACD negative"
        ]
      },
      "derivative_analysis": {
        "daily_expected_move": 0.08631976540129961,
        "atr_percent": 2.642796298353314,
        "support_level": 4.668,
        "resistance_level": 5.095,
        "tight_stop_loss": 4.505999912261963,
        "target_1r": 4.877999912261963,
        "target_2r": 5.063999912261963,
        "risk_reward_ratio": "1:2"
      },
      "expert_commentary": {
        "technical": "CSOP HS TECH RSI 48.1, MACD -0.00, trend bearish.",
        "volatility": "Annualized volatility 29.2% with ATR 2.6%.",
        "derivative": "Expected daily move HK$0.09; support HK$4.67, resistance HK$5.09."
      },
      "stale": false
    }
  },
  "schema_version": "v1"
}