{
  "timestamp": "2026-03-11T06:53:50.083638",
  "companies": {
    "tencent": {
      "price": 555.5,
      "open": 578.0,
      "high": 578.0,
      "low": 550.0,
      "volume": 41755850,
      "turnover": 23911108864.0,
      "change": 2.0,
      "change_pct": 0.36134,
      "amplitude": 5.0405040504050405,
      "ma_5": 528.9,
      "ma_10": 520.5,
      "ma_20": 528.35,
      "ma_50": 574.5,
      "ma_200": 582.469696969697,
      "ema_12": 529.5382719937024,
      "ema_26": 541.7163524005994,
      "rsi_14": 57.608695652173914,
      "rsi_6": 82.70676691729324,
      "macd": -12.178080406896925,
      "macd_signal": -10.960272366207233,
      "macd_histogram": -1.2178080406896914,
      "bb_upper": 562.5480993623914,
      "bb_middle": 528.35,
      "bb_lower": 494.15190063760855,
      "bb_width": 12.945244388148556,
      "atr": 19.085714285714285,
      "volatility": 37.514258500607355,
      "historical_vol_20": 37.514258500607355,
      "historical_vol_60": 29.99978580437247,
      "momentum_10": 8.203125,
      "stoch_k": 69.6969696969697,
      "stoch_d": 69.6969696969697,
      "williams_r": -30.303030303030308,
      "52w_high": 633.0,
      "52w_low": 502.0,
      "52w_position": 39.69465648854962,
      "avg_volume_20": 29529753.55,
      "volume_ratio": 1.435161757386221,
      "support_levels": [
        502.0
      ],
      "resistance_levels": [
        560.0
      ],
      "market_cap_billion": 665,
      "market_cap_display": "$665B",
      "market_cap_hkd": "HK$5193B",
      "pe_ratio": 15.722184,
      "pb_ratio": 3.7998075,
      "ps_ratio": 6.86007,
      "peg_ratio": 1.2,
      "ev_ebitda": 19.761,
      "fcf_yield": 19.45872037788763,
      "roe": 19.827999,
      "roa": 7.657000399999999,
      "gross_margin": 55.493,
      "op_margin": 32.952,
      "net_margin": 29.857,
      "revenue_growth": 15.4,
      "earnings_growth": 20.1,
      "revenue_billion": 729.84100864,
      "debt_equity": 0.3247,
      "cash_billion": 422.65100288,
      "net_cash_billion": 13.356007424,
      "fcf_billion": 129.573249024,
      "dividend_yield": 81.0,
      "beta": 0.826,
      "eps": 25.18,
      "source": {
        "quote": "akshare",
        "ohlcv": "akshare",
        "fundamentals": "yfinance"
      },
      "confidence": {
        "quote": 0.95,
        "ohlcv": 0.95,
        "fundamentals": 0.8
      },
      "source_timestamp": "2026-03-11T06:50:49.609653",
      "last_verified_at": "2026-03-11T06:50:51.690027",
      "is_estimated": true,
      "estimated_fields": [
        "peg_ratio"
      ],
      "company_name": "Tencent",
      "symbol": "00700",
      "industry": "Technology / Gaming / Social Media",
      "sector": "Communication Services",
      "technical_rating": {
        "score": -1,
        "rating": "Hold",
        "color": "#FF9800",
        "signals": [
          "MACD negative"
        ]
      },
      "derivative_analysis": {
        "daily_expected_move": 13.127443554462527,
        "atr_percent": 3.435772148643436,
        "support_level": 502.0,
        "resistance_level": 560.0,
        "tight_stop_loss": 526.8714285714286,
        "target_1r": 584.1285714285714,
        "target_2r": 612.7571428571429,
        "risk_reward_ratio": "1:2"
      },
      "expert_commentary": {
        "technical": "Tencent RSI 57.6, MACD -12.18, trend bullish.",
        "volatility": "Annualized volatility 37.5% with ATR 3.4%.",
        "derivative": "Expected daily move HK$13.13; support HK$502.00, resistance HK$560.00."
      },
      "stale": false
    },
    "baidu": {
      "price": 122.8,
      "open": 123.0,
      "high": 125.0,
      "low": 121.4,
      "volume": 5887272,
      "turnover": 740267376.0,
      "change": 2.0,
      "change_pct": 1.65563,
      "amplitude": 2.9315960912052073,
      "ma_5": 119.24000000000001,
      "ma_10": 119.41,
      "ma_20": 127.915,
      "ma_50": 137.75000000000003,
      "ma_200": 133.4272727272727,
      "ema_12": 122.61028945196914,
      "ema_26": 128.52483262660795,
      "rsi_14": 32.71889400921657,
      "rsi_6": 68.79432624113477,
      "macd": -5.914543174638808,
      "macd_signal": -5.323088857174928,
      "macd_histogram": -0.5914543174638807,
      "bb_upper": 147.206995749533,
      "bb_middle": 127.915,
      "bb_lower": 108.62300425046699,
      "bb_width": 30.163773989810434,
      "atr": 4.992857142857143,
      "volatility": 41.840944086314344,
      "historical_vol_20": 41.840944086314344,
      "historical_vol_60": 46.89230503426776,
      "momentum_10": -0.6482982171799119,
      "stoch_k": 47.16157205240175,
      "stoch_d": 47.16157205240175,
      "williams_r": -52.838427947598255,
      "52w_high": 160.5,
      "52w_low": 114.6,
      "52w_position": 17.429193899782135,
      "avg_volume_20": 12351437.9,
      "volume_ratio": 0.4874470526221081,
      "support_levels": [
        115.0
      ],
      "resistance_levels": [
        144.3
      ],
      "market_cap_billion": 54,
      "market_cap_display": "$54B",
      "market_cap_hkd": "HK$427B",
      "pe_ratio": 13.273542,
      "pb_ratio": 0.13858213,
      "ps_ratio": 2.668761,
      "peg_ratio": 1.2,
      "ev_ebitda": 18.272,
      "fcf_yield": 8.2087327327867,
      "roe": 1.9040000000000001,
      "roa": 1.4780000999999998,
      "gross_margin": 43.882,
      "op_margin": 6.691999999999999,
      "net_margin": 4.33,
      "revenue_growth": -4.1000000000000005,
      "earnings_growth": -72.3,
      "revenue_billion": 129.079001088,
      "debt_equity": 0.33506,
      "cash_billion": 115.267002368,
      "net_cash_billion": 18.190000128,
      "fcf_billion": 4.497375232,
      "dividend_yield": 0.6,
      "beta": 0.389,
      "eps": 1.67,
      "source": {
        "quote": "akshare",
        "ohlcv": "akshare",
        "fundamentals": "yfinance"
      },
      "confidence": {
        "quote": 0.95,
        "ohlcv": 0.95,
        "fundamentals": 0.8
      },
      "source_timestamp": "2026-03-11T06:51:25.585249",
      "last_verified_at": "2026-03-11T06:51:26.379238",
      "is_estimated": true,
      "estimated_fields": [
        "dividend_yield",
        "peg_ratio"
      ],
      "company_name": "Baidu",
      "symbol": "09888",
      "industry": "Technology / Search / AI",
      "sector": "Communication Services",
      "technical_rating": {
        "score": -3,
        "rating": "Sell",
        "color": "#F44336",
        "signals": [
          "Trend bearish",
          "MACD negative"
        ]
      },
      "derivative_analysis": {
        "daily_expected_move": 3.236678564806833,
        "atr_percent": 4.065844578873895,
        "support_level": 115.0,
        "resistance_level": 144.3,
        "tight_stop_loss": 115.31071428571428,
        "target_1r": 130.2892857142857,
        "target_2r": 137.7785714285714,
        "risk_reward_ratio": "1:2"
      },
      "expert_commentary": {
        "technical": "Baidu RSI 32.7, MACD -5.91, trend bearish.",
        "volatility": "Annualized volatility 41.8% with ATR 4.1%.",
        "derivative": "Expected daily move HK$3.24; support HK$115.00, resistance HK$144.30."
      },
      "stale": false
    },
    "jd": {
      "price": 108.8,
      "open": 109.0,
      "high": 110.5,
      "low": 108.0,
      "volume": 5620245,
      "turnover": 622808912.0,
      "change": 0.3,
      "change_pct": 0.2765,
      "amplitude": 2.297794117647059,
      "ma_5": 105.25,
      "ma_10": 103.43499999999999,
      "ma_20": 105.35749999999999,
      "ma_50": 110.06899999999997,
      "ma_200": 111.04772727272727,
      "ema_12": 105.1217315697373,
      "ema_26": 106.51867813916084,
      "rsi_14": 54.3613707165109,
      "rsi_6": 73.85057471264368,
      "macd": -1.396946569423534,
      "macd_signal": -1.2572519124811805,
      "macd_histogram": -0.1396946569423534,
      "bb_upper": 112.563141886744,
      "bb_middle": 105.35749999999999,
      "bb_lower": 98.15185811325597,
      "bb_width": 13.67846026480131,
      "atr": 3.6999999999999997,
      "volatility": 45.89424018087352,
      "historical_vol_20": 45.89424018087352,
      "historical_vol_60": 32.232171158694925,
      "momentum_10": 4.519230769230772,
      "stoch_k": 87.67123287671235,
      "stoch_d": 87.67123287671235,
      "williams_r": -12.328767123287657,
      "52w_high": 117.4,
      "52w_low": 96.95,
      "52w_position": 57.45721271393642,
      "avg_volume_20": 14491173.35,
      "volume_ratio": 0.39505607045960844,
      "support_levels": [
        96.95
      ],
      "resistance_levels": [
        110.0
      ],
      "market_cap_billion": 179,
      "market_cap_display": "$179B",
      "market_cap_hkd": "HK$1401B",
      "pe_ratio": 6.956246,
      "pb_ratio": 0.58572954,
      "ps_ratio": 0.2565081,
      "peg_ratio": 1.2,
      "ev_ebitda": 19.916,
      "fcf_yield": -10.082754782608694,
      "roe": 7.6240000000000006,
      "roa": 0.331,
      "gross_margin": 9.308,
      "op_margin": -1.2899999500000001,
      "net_margin": 1.5,
      "revenue_growth": 1.5,
      "earnings_growth": 35.8,
      "revenue_billion": 1309.085007872,
      "debt_equity": 0.36457,
      "cash_billion": 213.231992832,
      "net_cash_billion": 106.12699136,
      "fcf_billion": -18.114625536,
      "dividend_yield": 360.0,
      "beta": 0.454,
      "eps": 12.05,
      "source": {
        "quote": "akshare",
        "ohlcv": "akshare",
        "fundamentals": "yfinance"
      },
      "confidence": {
        "quote": 0.95,
        "ohlcv": 0.95,
        "fundamentals": 0.8
      },
      "source_timestamp": "2026-03-11T06:52:01.137642",
      "last_verified_at": "2026-03-11T06:52:02.815435",
      "is_estimated": true,
      "estimated_fields": [
        "earnings_growth",
        "peg_ratio"
      ],
      "company_name": "JD.com",
      "symbol": "09618",
      "industry": "E-commerce / Logistics",
      "sector": "Consumer Discretionary",
      "technical_rating": {
        "score": -1,
        "rating": "Hold",
        "color": "#FF9800",
        "signals": [
          "MACD negative"
        ]
      },
      "derivative_analysis": {
        "daily_expected_move": 3.14547913781426,
        "atr_percent": 3.4007352941176467,
        "support_level": 96.95,
        "resistance_level": 110.0,
        "tight_stop_loss": 103.25,
        "target_1r": 114.35,
        "target_2r": 119.89999999999999,
        "risk_reward_ratio": "1:2"
      },
      "expert_commentary": {
        "technical": "JD.com RSI 54.4, MACD -1.40, trend bullish.",
        "volatility": "Annualized volatility 45.9% with ATR 3.4%.",
        "derivative": "Expected daily move HK$3.15; support HK$96.95, resistance HK$110.00."
      },
      "stale": false
    },
    "alibaba": {
      "price": 133.9,
      "open": 135.5,
      "high": 136.1,
      "low": 132.6,
      "volume": 49975828,
      "turnover": 6807314176.0,
      "change": 0.4,
      "change_pct": 0.29963,
      "amplitude": 2.6138909634055265,
      "ma_5": 130.54000000000002,
      "ma_10": 133.96999999999997,
      "ma_20": 144.125,
      "ma_50": 152.536,
      "ma_200": 151.98181818181817,
      "ema_12": 136.73080061688555,
      "ema_26": 144.09753565080518,
      "rsi_14": 28.96825396825399,
      "rsi_6": 46.70050761421317,
      "macd": -7.366735033919639,
      "macd_signal": -6.6300615305276756,
      "macd_histogram": -0.7366735033919634,
      "bb_upper": 166.8472248030425,
      "bb_middle": 144.125,
      "bb_lower": 121.40277519695749,
      "bb_width": 31.531274661637475,
      "atr": 5.4214285714285735,
      "volatility": 40.26209897299516,
      "historical_vol_20": 40.26209897299516,
      "historical_vol_60": 40.187835740322186,
      "momentum_10": -6.643356643356643,
      "stoch_k": 29.787234042553195,
      "stoch_d": 29.787234042553195,
      "williams_r": -70.2127659574468,
      "52w_high": 173.5,
      "52w_low": 126.3,
      "52w_position": 15.254237288135597,
      "avg_volume_20": 81945239.2,
      "volume_ratio": 0.618756678179298,
      "support_levels": [
        126.3
      ],
      "resistance_levels": [
        160.5
      ],
      "market_cap_billion": 403,
      "market_cap_display": "$403B",
      "market_cap_hkd": "HK$3146B",
      "pe_ratio": 15.442763,
      "pb_ratio": 0.26575583,
      "ps_ratio": 2.5269341,
      "peg_ratio": 1.2,
      "ev_ebitda": 15.505,
      "fcf_yield": -12.26758887304276,
      "roe": 11.190999999999999,
      "roa": 4.0329999999999995,
      "gross_margin": 41.173,
      "op_margin": 2.165,
      "net_margin": 12.1879995,
      "revenue_growth": 4.8,
      "earnings_growth": -51.800000000000004,
      "revenue_billion": 1012.055015424,
      "debt_equity": 0.27249,
      "cash_billion": 373.572009984,
      "net_cash_billion": 70.624018432,
      "fcf_billion": -49.489498112,
      "dividend_yield": 77.0,
      "beta": 0.435,
      "eps": 7.41,
      "source": {
        "quote": "akshare",
        "ohlcv": "akshare",
        "fundamentals": "yfinance"
      },
      "confidence": {
        "quote": 0.95,
        "ohlcv": 0.95,
        "fundamentals": 0.8
      },
      "source_timestamp": "2026-03-11T06:52:37.172080",
      "last_verified_at": "2026-03-11T06:52:38.461341",
      "is_estimated": true,
      "estimated_fields": [
        "peg_ratio"
      ],
      "company_name": "Alibaba",
      "symbol": "09988",
      "industry": "E-commerce / Cloud",
      "sector": "Consumer Discretionary",
      "technical_rating": {
        "score": -1,
        "rating": "Hold",
        "color": "#FF9800",
        "signals": [
          "RSI oversold",
          "Trend bearish",
          "MACD negative"
        ]
      },
      "derivative_analysis": {
        "daily_expected_move": 3.3960706674246453,
        "atr_percent": 4.048863757601623,
        "support_level": 126.3,
        "resistance_level": 160.5,
        "tight_stop_loss": 125.76785714285714,
        "target_1r": 142.03214285714287,
        "target_2r": 150.1642857142857,
        "risk_reward_ratio": "1:2"
      },
      "expert_commentary": {
        "technical": "Alibaba RSI 29.0, MACD -7.37, trend bearish.",
        "volatility": "Annualized volatility 40.3% with ATR 4.0%.",
        "derivative": "Expected daily move HK$3.40; support HK$126.30, resistance HK$160.50."
      },
      "stale": false
    },
    "xiaomi": {
      "price": 33.4,
      "open": 33.62,
      "high": 33.98,
      "low": 33.14,
      "volume": 100263745,
      "turnover": 3455588096.0,
      "change": -0.22,
      "change_pct": -0.65437,
      "amplitude": 2.5149700598802287,
      "ma_5": 33.252,
      "ma_10": 33.306000000000004,
      "ma_20": 34.711,
      "ma_50": 36.0864,
      "ma_200": 37.34030303030303,
      "ema_12": 33.74607142001746,
      "ema_26": 34.66750905650219,
      "rsi_14": 33.26612903225811,
      "rsi_6": 86.06557377049194,
      "macd": -0.9214376364847325,
      "macd_signal": -0.8292938728362593,
      "macd_histogram": -0.09214376364847321,
      "bb_upper": 38.056910339504036,
      "bb_middle": 34.711,
      "bb_lower": 31.365089660495965,
      "bb_width": 19.278674423116797,
      "atr": 1.282857142857143,
      "volatility": 39.623915216239716,
      "historical_vol_20": 39.623915216239716,
      "historical_vol_60": 31.748461685434208,
      "momentum_10": -5.230244457077875,
      "stoch_k": 37.80918727915201,
      "stoch_d": 37.80918727915201,
      "williams_r": -62.19081272084799,
      "52w_high": 42.96,
      "52w_low": 31.58,
      "52w_position": 15.46572934973642,
      "avg_volume_20": 154739610.65,
      "volume_ratio": 0.6669368273998562,
      "support_levels": [
        31.58
      ],
      "resistance_levels": [
        37.1
      ],
      "market_cap_billion": 104,
      "market_cap_display": "$104B",
      "market_cap_hkd": "HK$811B",
      "pe_ratio": 18.413029,
      "pb_ratio": 2.8803172,
      "ps_ratio": 1.9259764,
      "peg_ratio": 1.2,
      "ev_ebitda": 18.825,
      "fcf_yield": 31.128718998151843,
      "roe": 19.855,
      "roa": 5.269,
      "gross_margin": 22.23,
      "op_margin": 8.488,
      "net_margin": 9.818999999999999,
      "revenue_growth": 22.3,
      "earnings_growth": 118.7,
      "revenue_billion": 449.375305728,
      "debt_equity": 0.10389,
      "cash_billion": 110.150320128,
      "net_cash_billion": 82.561370112,
      "fcf_billion": 32.390629376,
      "dividend_yield": 0.1,
      "beta": 0.779,
      "eps": 1.63,
      "source": {
        "quote": "akshare",
        "ohlcv": "akshare",
        "fundamentals": "yfinance"
      },
      "confidence": {
        "quote": 0.95,
        "ohlcv": 0.95,
        "fundamentals": 0.8
      },
      "source_timestamp": "2026-03-11T06:53:09.810009",
      "last_verified_at": "2026-03-11T06:53:11.342958",
      "is_estimated": true,
      "estimated_fields": [
        "dividend_yield",
        "peg_ratio"
      ],
      "company_name": "Xiaomi",
      "symbol": "01810",
      "industry": "Consumer Electronics / EV / IoT",
      "sector": "Information Technology",
      "technical_rating": {
        "score": -3,
        "rating": "Sell",
        "color": "#F44336",
        "signals": [
          "Trend bearish",
          "MACD negative"
        ]
      },
      "derivative_analysis": {
        "daily_expected_move": 0.833688060985271,
        "atr_percent": 3.8408896492728837,
        "support_level": 31.58,
        "resistance_level": 37.1,
        "tight_stop_loss": 31.475714285714282,
        "target_1r": 35.324285714285715,
        "target_2r": 37.248571428571424,
        "risk_reward_ratio": "1:2"
      },
      "expert_commentary": {
        "technical": "Xiaomi RSI 33.3, MACD -0.92, trend bearish.",
        "volatility": "Annualized volatility 39.6% with ATR 3.8%.",
        "derivative": "Expected daily move HK$0.83; support HK$31.58, resistance HK$37.10."
      },
      "stale": false
    },
    "meituan": {
      "price": 77.4,
      "open": 79.15,
      "high": 79.6,
      "low": 76.65,
      "volume": 29569050,
      "turnover": 2344436256.0,
      "change": -1.7,
      "change_pct": -2.14918,
      "amplitude": 3.8113695090439124,
      "ma_5": 77.25999999999999,
      "ma_10": 77.63500000000002,
      "ma_20": 81.1975,
      "ma_50": 92.24300000000001,
      "ma_200": 94.15530303030303,
      "ema_12": 79.04963549046822,
      "ema_26": 83.45439990250645,
      "rsi_14": 40.789473684210535,
      "rsi_6": 59.74025974025975,
      "macd": -4.404764412038233,
      "macd_signal": -3.96428797083441,
      "macd_histogram": -0.4404764412038231,
      "bb_upper": 90.31350104212368,
      "bb_middle": 81.1975,
      "bb_lower": 72.08149895787633,
      "bb_width": 22.453895851777876,
      "atr": 3.3607142857142875,
      "volatility": 41.883819150298415,
      "historical_vol_20": 41.883819150298415,
      "historical_vol_60": 33.119549673066196,
      "momentum_10": -4.101926662523303,
      "stoch_k": 25.53956834532381,
      "stoch_d": 25.53956834532381,
      "williams_r": -74.4604316546762,
      "52w_high": 106.1,
      "52w_low": 74.5,
      "52w_position": 8.386075949367108,
      "avg_volume_20": 55232575.85,
      "volume_ratio": 0.547586230309771,
      "support_levels": [
        74.5
      ],
      "resistance_levels": [
        91.05
      ],
      "market_cap_billion": 560,
      "market_cap_display": "$560B",
      "market_cap_hkd": "HK$4373B",
      "pe_ratio": 36.985878,
      "pb_ratio": 2.3949902,
      "ps_ratio": 1.3043785,
      "peg_ratio": 1.2,
      "ev_ebitda": 109.181,
      "fcf_yield": 0.6780380489812718,
      "roe": -1.2130001,
      "roa": -0.911,
      "gross_margin": 33.516,
      "op_margin": -20.095,
      "net_margin": -0.54900004,
      "revenue_growth": 2.0,
      "earnings_growth": 57.2,
      "revenue_billion": 362.373021696,
      "debt_equity": 0.30629,
      "cash_billion": 141.28775168,
      "net_cash_billion": 90.021801984,
      "fcf_billion": 3.8014464,
      "dividend_yield": 0.0,
      "beta": 0.263,
      "eps": 5.32,
      "source": {
        "quote": "akshare",
        "ohlcv": "akshare",
        "fundamentals": "yfinance"
      },
      "confidence": {
        "quote": 0.95,
        "ohlcv": 0.95,
        "fundamentals": 0.8
      },
      "source_timestamp": "2026-03-11T06:53:45.812585",
      "last_verified_at": "2026-03-11T06:53:47.055250",
      "is_estimated": true,
      "estimated_fields": [
        "earnings_growth",
        "dividend_yield",
        "peg_ratio"
      ],
      "company_name": "Meituan",
      "symbol": "03690",
      "industry": "Local Services",
      "sector": "Consumer Discretionary",
      "technical_rating": {
        "score": -3,
        "rating": "Sell",
        "color": "#F44336",
        "signals": [
          "Trend bearish",
          "MACD negative"
        ]
      },
      "derivative_analysis": {
        "daily_expected_move": 2.042146836625565,
        "atr_percent": 4.342008121077891,
        "support_level": 74.5,
        "resistance_level": 91.05,
        "tight_stop_loss": 72.35892857142858,
        "target_1r": 82.44107142857143,
        "target_2r": 87.48214285714286,
        "risk_reward_ratio": "1:2"
      },
      "expert_commentary": {
        "technical": "Meituan RSI 40.8, MACD -4.40, trend bearish.",
        "volatility": "Annualized volatility 41.9% with ATR 4.3%.",
        "derivative": "Expected daily move HK$2.04; support HK$74.50, resistance HK$91.05."
      },
      "stale": false
    }
  },
  "schema_version": "v1"
}