{
  "timestamp": "2026-05-26T05:56:30.119745",
  "companies": {
    "tencent": {
      "price": 438.6,
      "open": 438.0,
      "high": 441.0,
      "low": 432.0,
      "volume": 21991558,
      "turnover": 9645497338.800001,
      "change": -2.8,
      "change_pct": -0.63435,
      "amplitude": 2.0519835841313268,
      "ma_5": 446.8,
      "ma_10": 450.3706909179688,
      "ma_20": 458.5069320678711,
      "ma_50": 486.8493383789062,
      "ma_200": 490.50682197182863,
      "ema_12": 452.04987297827233,
      "ema_26": 464.44184883889875,
      "rsi_14": 35.366280721268396,
      "rsi_6": 29.729713010809007,
      "macd": -12.391975860626417,
      "macd_signal": -11.152778274563776,
      "macd_histogram": -1.239197586062641,
      "bb_upper": 479.38942084507744,
      "bb_middle": 458.5069320678711,
      "bb_lower": 437.6244432906648,
      "bb_width": 9.108908640934212,
      "atr": 12.795246184857897,
      "volatility": 25.906570528767546,
      "historical_vol_20": 25.906570528767546,
      "historical_vol_60": 0.0,
      "momentum_10": -2.994802279236985,
      "stoch_k": 14.726024698943533,
      "stoch_d": 14.726024698943533,
      "williams_r": -85.27397530105647,
      "52w_high": 552.06787109375,
      "52w_low": 438.3999938964844,
      "52w_position": 0.0,
      "avg_volume_20": 29821623.9,
      "volume_ratio": 0.7388253260078168,
      "support_levels": [
        438.3999938964844
      ],
      "resistance_levels": [
        473.6811828613281
      ],
      "market_cap_billion": 525,
      "market_cap_display": "$525B",
      "market_cap_hkd": "HK$4100B",
      "pe_ratio": 11.454791,
      "pb_ratio": 3.045553,
      "ps_ratio": 5.154058,
      "peg_ratio": 1.32,
      "ev_ebitda": 14.227,
      "fcf_yield": 24.742695576932924,
      "roe": 20.515,
      "roa": 7.9169996000000005,
      "gross_margin": 56.449000000000005,
      "op_margin": 34.294999999999995,
      "net_margin": 30.606002,
      "revenue_growth": 9.1,
      "earnings_growth": 22.900000000000002,
      "revenue_billion": 768.201981952,
      "debt_equity": 0.33468000000000003,
      "cash_billion": 459.714985984,
      "net_cash_billion": 54.203973632,
      "fcf_billion": 130.08662528,
      "dividend_yield": 120.0,
      "beta": 0.753,
      "eps": 27.81,
      "source": {
        "quote": "akshare",
        "ohlcv": "yfinance",
        "fundamentals": "yfinance"
      },
      "confidence": {
        "quote": 0.95,
        "ohlcv": 0.85,
        "fundamentals": 0.8
      },
      "source_timestamp": "2026-05-26T05:54:12.657804",
      "last_verified_at": "2026-05-26T05:54:14.216933",
      "is_estimated": false,
      "estimated_fields": [],
      "company_name": "Tencent",
      "symbol": "00700",
      "industry": "Technology / Gaming / Social Media",
      "sector": "Communication Services",
      "technical_rating": {
        "score": -3,
        "rating": "Sell",
        "color": "#F44336",
        "signals": [
          "Trend bearish",
          "MACD negative"
        ]
      },
      "derivative_analysis": {
        "daily_expected_move": 7.157778955766244,
        "atr_percent": 2.917292791805266,
        "support_level": 438.3999938964844,
        "resistance_level": 473.6811828613281,
        "tight_stop_loss": 419.4071307227132,
        "target_1r": 457.79286927728685,
        "target_2r": 476.9857385545737,
        "risk_reward_ratio": "1:2"
      },
      "expert_commentary": {
        "technical": "Tencent RSI 35.4, MACD -12.39, trend bearish.",
        "volatility": "Annualized volatility 25.9% with ATR 2.9%.",
        "derivative": "Expected daily move HK$7.16; support HK$438.40, resistance HK$473.68."
      },
      "stale": false
    },
    "alibaba": {
      "price": 128.4,
      "open": 127.2,
      "high": 128.8,
      "low": 124.3,
      "volume": 54605243,
      "turnover": 7011313201.200001,
      "change": 1.4,
      "change_pct": 1.10236,
      "amplitude": 3.5046728971962726,
      "ma_5": 129.3,
      "ma_10": 131.45,
      "ma_20": 131.93499908447265,
      "ma_50": 129.72999938964844,
      "ma_200": 130.38474493511652,
      "ema_12": 130.81107155434333,
      "ema_26": 131.27562504790933,
      "rsi_14": 46.40199159441142,
      "rsi_6": 33.05087375828563,
      "macd": -0.46455349356600095,
      "macd_signal": -0.4180981442094009,
      "macd_histogram": -0.04645534935660006,
      "bb_upper": 139.96575601015337,
      "bb_middle": 131.93499908447265,
      "bb_lower": 123.90424215879193,
      "bb_width": 12.173808286516834,
      "atr": 5.4428558349609375,
      "volatility": 45.055480761584164,
      "historical_vol_20": 45.055480761584164,
      "historical_vol_60": 0.0,
      "momentum_10": -3.7509376485599906,
      "stoch_k": 20.304571673331736,
      "stoch_d": 20.304571673331736,
      "williams_r": -79.69542832666826,
      "52w_high": 143.0,
      "52w_low": 118.5,
      "52w_position": 40.00001245615434,
      "avg_volume_20": 82298971.1,
      "volume_ratio": 0.6651145484369245,
      "support_levels": [
        126.0
      ],
      "resistance_levels": [
        140.89999389648438
      ],
      "market_cap_billion": 386,
      "market_cap_display": "$386B",
      "market_cap_hkd": "HK$3017B",
      "pe_ratio": 13.234325,
      "pb_ratio": 1.9487286,
      "ps_ratio": 2.4055321,
      "peg_ratio": 0.44,
      "ev_ebitda": 21.811,
      "fcf_yield": -11.393224361105586,
      "roe": 9.2159994,
      "roa": 2.12,
      "gross_margin": 39.811,
      "op_margin": 1.01499995,
      "net_margin": 10.12,
      "revenue_growth": 2.9000000000000004,
      "earnings_growth": 104.1,
      "revenue_billion": 1023.67002624,
      "debt_equity": 0.25014,
      "cash_billion": 316.819996672,
      "net_cash_billion": 35.098001408,
      "fcf_billion": -44.07425024,
      "dividend_yield": 81.0,
      "beta": 0.494,
      "eps": 6.34,
      "source": {
        "quote": "akshare",
        "ohlcv": "yfinance",
        "fundamentals": "yfinance"
      },
      "confidence": {
        "quote": 0.95,
        "ohlcv": 0.85,
        "fundamentals": 0.8
      },
      "source_timestamp": "2026-05-26T05:54:46.416361",
      "last_verified_at": "2026-05-26T05:54:47.239194",
      "is_estimated": false,
      "estimated_fields": [],
      "company_name": "Alibaba",
      "symbol": "09988",
      "industry": "E-commerce / Cloud",
      "sector": "Consumer Discretionary",
      "technical_rating": {
        "score": -1,
        "rating": "Hold",
        "color": "#FF9800",
        "signals": [
          "MACD negative"
        ]
      },
      "derivative_analysis": {
        "daily_expected_move": 3.64428540303712,
        "atr_percent": 4.238984295140917,
        "support_level": 126.0,
        "resistance_level": 140.89999389648438,
        "tight_stop_loss": 120.2357162475586,
        "target_1r": 136.5642837524414,
        "target_2r": 144.72856750488282,
        "risk_reward_ratio": "1:2"
      },
      "expert_commentary": {
        "technical": "Alibaba RSI 46.4, MACD -0.46, trend bearish.",
        "volatility": "Annualized volatility 45.1% with ATR 4.2%.",
        "derivative": "Expected daily move HK$3.64; support HK$126.00, resistance HK$140.90."
      },
      "stale": false
    },
    "xiaomi": {
      "price": 29.84,
      "open": 30.0,
      "high": 30.52,
      "low": 29.3,
      "volume": 94655212,
      "turnover": 2824511526.08,
      "change": -0.16,
      "change_pct": -0.53333,
      "amplitude": 4.0884718498659485,
      "ma_5": 30.051999664306642,
      "ma_10": 30.659999656677247,
      "ma_20": 30.676999855041505,
      "ma_50": 31.77759998321533,
      "ma_200": 32.01016946566307,
      "ema_12": 30.487860279850903,
      "ema_26": 30.944715188896936,
      "rsi_14": 42.85715502134696,
      "rsi_6": 21.794862389807932,
      "macd": -0.456854909046033,
      "macd_signal": -0.4111694181414297,
      "macd_histogram": -0.045685490904603276,
      "bb_upper": 32.20499326404968,
      "bb_middle": 30.676999855041505,
      "bb_lower": 29.14900644603333,
      "bb_width": 9.961817754203004,
      "atr": 0.9314286368233817,
      "volatility": 36.6155378076323,
      "historical_vol_20": 36.6155378076323,
      "historical_vol_60": 0.0,
      "momentum_10": -5.212967060949067,
      "stoch_k": 14.525145022355392,
      "stoch_d": 14.525145022355392,
      "williams_r": -85.47485497764461,
      "52w_high": 36.31999969482422,
      "52w_low": 29.020000457763672,
      "52w_position": 10.958894803702451,
      "avg_volume_20": 141741730.35,
      "volume_ratio": 0.6686443841624796,
      "support_levels": [
        29.020000457763672
      ],
      "resistance_levels": [
        31.799999237060547
      ],
      "market_cap_billion": 92,
      "market_cap_display": "$92B",
      "market_cap_hkd": "HK$725B",
      "pe_ratio": 16.235521,
      "pb_ratio": 2.5171857,
      "ps_ratio": 1.6827958,
      "peg_ratio": 2.35,
      "ev_ebitda": 18.352,
      "fcf_yield": 17.40250887498759,
      "roe": 18.25,
      "roa": 4.441,
      "gross_margin": 22.263001,
      "op_margin": 2.181,
      "net_margin": 9.1070004,
      "revenue_growth": 7.3,
      "earnings_growth": -33.7,
      "revenue_billion": 457.286680576,
      "debt_equity": 0.15709,
      "cash_billion": 107.696586752,
      "net_cash_billion": 65.858691072,
      "fcf_billion": 16.177907712,
      "dividend_yield": 0.1,
      "beta": 0.725,
      "eps": 1.8,
      "source": {
        "quote": "akshare",
        "ohlcv": "yfinance",
        "fundamentals": "yfinance"
      },
      "confidence": {
        "quote": 0.95,
        "ohlcv": 0.85,
        "fundamentals": 0.8
      },
      "source_timestamp": "2026-05-26T05:55:18.189924",
      "last_verified_at": "2026-05-26T05:55:19.356709",
      "is_estimated": true,
      "estimated_fields": [
        "dividend_yield"
      ],
      "company_name": "Xiaomi",
      "symbol": "01810",
      "industry": "Consumer Electronics / EV / IoT",
      "sector": "Information Technology",
      "technical_rating": {
        "score": -3,
        "rating": "Sell",
        "color": "#F44336",
        "signals": [
          "Trend bearish",
          "MACD negative"
        ]
      },
      "derivative_analysis": {
        "daily_expected_move": 0.6882781232501826,
        "atr_percent": 3.1214096408290275,
        "support_level": 29.020000457763672,
        "resistance_level": 31.799999237060547,
        "tight_stop_loss": 28.442857044764928,
        "target_1r": 31.237142955235072,
        "target_2r": 32.63428591047015,
        "risk_reward_ratio": "1:2"
      },
      "expert_commentary": {
        "technical": "Xiaomi RSI 42.9, MACD -0.46, trend bearish.",
        "volatility": "Annualized volatility 36.6% with ATR 3.1%.",
        "derivative": "Expected daily move HK$0.69; support HK$29.02, resistance HK$31.80."
      },
      "stale": false
    },
    "meituan": {
      "price": 79.0,
      "open": 79.95,
      "high": 80.5,
      "low": 77.0,
      "volume": 43185044,
      "turnover": 3499070192.0,
      "change": -2.35,
      "change_pct": -2.88875,
      "amplitude": 4.430379746835443,
      "ma_5": 81.66999999999999,
      "ma_10": 83.065,
      "ma_20": 83.11749999999998,
      "ma_50": 83.139,
      "ma_200": 82.34924242424243,
      "ema_12": 82.48858975329335,
      "ema_26": 83.13393882806743,
      "rsi_14": 36.88760806916424,
      "rsi_6": 16.36363636363626,
      "macd": -0.6453490747740744,
      "macd_signal": -0.580814167296667,
      "macd_histogram": -0.06453490747740742,
      "bb_upper": 86.74258965406372,
      "bb_middle": 83.11749999999998,
      "bb_lower": 79.49241034593624,
      "bb_width": 8.722807240505896,
      "atr": 3.046428571428571,
      "volatility": 30.61349016067133,
      "historical_vol_20": 30.61349016067133,
      "historical_vol_60": 47.58896879128321,
      "momentum_10": -6.120023767082597,
      "stoch_k": 13.937282229965163,
      "stoch_d": 13.937282229965163,
      "williams_r": -86.06271777003485,
      "52w_high": 90.0,
      "52w_low": 74.5,
      "52w_position": 29.03225806451613,
      "avg_volume_20": 36976802.1,
      "volume_ratio": 1.2062992597188387,
      "support_levels": [
        79.0
      ],
      "resistance_levels": [
        87.6
      ],
      "market_cap_billion": 572,
      "market_cap_display": "$572B",
      "market_cap_hkd": "HK$4463B",
      "pe_ratio": 14.871371,
      "pb_ratio": 2.7687616,
      "ps_ratio": 1.3360592,
      "peg_ratio": 16.84,
      "ev_ebitda": -17.327,
      "fcf_yield": -2.9180272029752437,
      "roe": -14.434,
      "roa": -5.778999600000001,
      "gross_margin": 30.425,
      "op_margin": -21.325001,
      "net_margin": -6.401,
      "revenue_growth": 2.8000000000000003,
      "earnings_growth": 57.2,
      "revenue_billion": 364.854738944,
      "debt_equity": 0.57368,
      "cash_billion": 166.833700864,
      "net_cash_billion": 80.214597632,
      "fcf_billion": -16.698223616,
      "dividend_yield": 0.0,
      "beta": 0.201,
      "eps": -4.51,
      "source": {
        "quote": "akshare",
        "ohlcv": "akshare",
        "fundamentals": "yfinance"
      },
      "confidence": {
        "quote": 0.95,
        "ohlcv": 0.95,
        "fundamentals": 0.8
      },
      "source_timestamp": "2026-05-26T05:55:51.547092",
      "last_verified_at": "2026-05-26T05:55:53.052819",
      "is_estimated": true,
      "estimated_fields": [
        "earnings_growth",
        "dividend_yield"
      ],
      "company_name": "Meituan",
      "symbol": "03690",
      "industry": "Local Services",
      "sector": "Consumer Discretionary",
      "technical_rating": {
        "score": -3,
        "rating": "Sell",
        "color": "#F44336",
        "signals": [
          "Trend bearish",
          "MACD negative"
        ]
      },
      "derivative_analysis": {
        "daily_expected_move": 1.523490203947588,
        "atr_percent": 3.856238698010849,
        "support_level": 79.0,
        "resistance_level": 87.6,
        "tight_stop_loss": 74.43035714285715,
        "target_1r": 83.56964285714285,
        "target_2r": 88.1392857142857,
        "risk_reward_ratio": "1:2"
      },
      "expert_commentary": {
        "technical": "Meituan RSI 36.9, MACD -0.65, trend bearish.",
        "volatility": "Annualized volatility 30.6% with ATR 3.9%.",
        "derivative": "Expected daily move HK$1.52; support HK$79.00, resistance HK$87.60."
      },
      "stale": false
    },
    "baidu": {
      "price": 128.2,
      "open": 128.5,
      "high": 129.6,
      "low": 127.1,
      "volume": 8435893,
      "turnover": 1081481482.6,
      "change": 1.7,
      "change_pct": 1.34387,
      "amplitude": 1.9500780031201248,
      "ma_5": 132.05999755859375,
      "ma_10": 135.50999755859374,
      "ma_20": 131.3199993133545,
      "ma_50": 121.75599990844727,
      "ma_200": 121.80819652119621,
      "ema_12": 132.47253267689362,
      "ema_26": 129.33125291826926,
      "rsi_14": 55.03731003368322,
      "rsi_6": 18.407953400699768,
      "macd": 3.141279758624364,
      "macd_signal": 2.827151782761928,
      "macd_histogram": 0.31412797586243624,
      "bb_upper": 146.90070258819475,
      "bb_middle": 131.3199993133545,
      "bb_lower": 115.73929603851421,
      "bb_width": 23.729368498794685,
      "atr": 5.907141549246652,
      "volatility": 49.86756808930353,
      "historical_vol_20": 49.86756808930353,
      "historical_vol_60": 43.79677879431496,
      "momentum_10": -9.013482965494342,
      "stoch_k": 20.5645137721364,
      "stoch_d": 20.5645137721364,
      "williams_r": -79.4354862278636,
      "52w_high": 145.1999969482422,
      "52w_low": 105.5999984741211,
      "52w_position": 57.0707054165428,
      "avg_volume_20": 13770344.95,
      "volume_ratio": 0.6126203105754443,
      "support_levels": [
        118.69999694824219
      ],
      "resistance_levels": [
        145.1999969482422
      ],
      "market_cap_billion": 57,
      "market_cap_display": "$57B",
      "market_cap_hkd": "HK$446B",
      "pe_ratio": 14.484476,
      "pb_ratio": 1.1287605,
      "ps_ratio": 2.7114043,
      "peg_ratio": 0.78,
      "ev_ebitda": 14.624,
      "fcf_yield": 13.914428154284794,
      "roe": 0.319,
      "roa": 1.2519999,
      "gross_margin": 42.084998,
      "op_margin": 9.955,
      "net_margin": 1.023,
      "revenue_growth": -1.2,
      "earnings_growth": -59.3,
      "revenue_billion": 128.701997056,
      "debt_equity": 0.322,
      "cash_billion": 116.890001408,
      "net_cash_billion": 22.754000896,
      "fcf_billion": 7.958624768,
      "dividend_yield": 0.6,
      "beta": 0.524,
      "eps": -0.15,
      "source": {
        "quote": "akshare",
        "ohlcv": "yfinance",
        "fundamentals": "yfinance"
      },
      "confidence": {
        "quote": 0.95,
        "ohlcv": 0.85,
        "fundamentals": 0.8
      },
      "source_timestamp": "2026-05-22T09:48:23.454256",
      "last_verified_at": "2026-05-22T09:48:24.317140",
      "is_estimated": true,
      "estimated_fields": [
        "dividend_yield"
      ],
      "company_name": "Baidu",
      "symbol": "09888",
      "industry": "Technology / Search / AI",
      "sector": "Communication Services",
      "technical_rating": {
        "score": 1,
        "rating": "Hold",
        "color": "#FF9800",
        "signals": [
          "MACD positive"
        ]
      },
      "derivative_analysis": {
        "daily_expected_move": 4.027225462897786,
        "atr_percent": 4.607754718601133,
        "support_level": 118.69999694824219,
        "resistance_level": 145.1999969482422,
        "tight_stop_loss": 119.33928767613001,
        "target_1r": 137.06071232386998,
        "target_2r": 145.92142464773994,
        "risk_reward_ratio": "1:2"
      },
      "expert_commentary": {
        "technical": "Baidu RSI 55.0, MACD 3.14, trend bearish.",
        "volatility": "Annualized volatility 49.9% with ATR 4.6%.",
        "derivative": "Expected daily move HK$4.03; support HK$118.70, resistance HK$145.20."
      },
      "stale": false
    },
    "jd": {
      "price": 121.7,
      "open": 123.5,
      "high": 123.5,
      "low": 121.1,
      "volume": 8256004,
      "turnover": 1004755686.8000001,
      "change": -1.8,
      "change_pct": -1.45749,
      "amplitude": 1.9720624486442118,
      "ma_5": 125.08000030517579,
      "ma_10": 124.85000076293946,
      "ma_20": 121.00000076293945,
      "ma_50": 116.4017253112793,
      "ma_200": 113.97954922035092,
      "ema_12": 123.55755779072652,
      "ema_26": 120.8988150192503,
      "rsi_14": 58.78134338480116,
      "rsi_6": 15.57376741626436,
      "macd": 2.658742771476213,
      "macd_signal": 2.392868494328592,
      "macd_histogram": 0.265874277147621,
      "bb_upper": 130.62995464230823,
      "bb_middle": 121.00000076293945,
      "bb_lower": 111.37004688357067,
      "bb_width": 15.91727903908956,
      "atr": 3.5928589957101003,
      "volatility": 37.18087695841784,
      "historical_vol_20": 37.18087695841784,
      "historical_vol_60": 37.4630938344859,
      "momentum_10": 2.7004193656052213,
      "stoch_k": 40.9835997228404,
      "stoch_d": 40.9835997228404,
      "williams_r": -59.0164002771596,
      "52w_high": 130.10000610351562,
      "52w_low": 96.51679992675781,
      "52w_position": 74.98747108581045,
      "avg_volume_20": 10822665.65,
      "volume_ratio": 0.7633520490397853,
      "support_levels": [
        115.30000305175781
      ],
      "resistance_levels": [
        130.10000610351562
      ],
      "market_cap_billion": 200,
      "market_cap_display": "$200B",
      "market_cap_hkd": "HK$1567B",
      "pe_ratio": 7.404077,
      "pb_ratio": 1.339394,
      "ps_ratio": 0.25114563,
      "peg_ratio": 1.05,
      "ev_ebitda": 43.604,
      "fcf_yield": 3.4861860291828495,
      "roe": 6.0040000000000004,
      "roa": -0.27799999999999997,
      "gross_margin": 9.32,
      "op_margin": 1.206,
      "net_margin": 1.04600005,
      "revenue_growth": 4.9,
      "earnings_growth": -50.7,
      "revenue_billion": 1323.697045504,
      "debt_equity": 0.38478,
      "cash_billion": 202.132996096,
      "net_cash_billion": 94.112997376,
      "fcf_billion": 7.0058752,
      "dividend_yield": 317.0,
      "beta": 0.403,
      "eps": 5.32,
      "source": {
        "quote": "akshare",
        "ohlcv": "yfinance",
        "fundamentals": "yfinance"
      },
      "confidence": {
        "quote": 0.95,
        "ohlcv": 0.85,
        "fundamentals": 0.8
      },
      "source_timestamp": "2026-05-22T09:49:09.633906",
      "last_verified_at": "2026-05-22T09:49:10.990736",
      "is_estimated": false,
      "estimated_fields": [],
      "company_name": "JD.com",
      "symbol": "09618",
      "industry": "E-commerce / Logistics",
      "sector": "Consumer Discretionary",
      "technical_rating": {
        "score": 3,
        "rating": "Buy",
        "color": "#4CAF50",
        "signals": [
          "Trend bullish",
          "MACD positive"
        ]
      },
      "derivative_analysis": {
        "daily_expected_move": 2.8504270897244233,
        "atr_percent": 2.952225961963928,
        "support_level": 115.30000305175781,
        "resistance_level": 130.10000610351562,
        "tight_stop_loss": 116.31071150643486,
        "target_1r": 127.08928849356515,
        "target_2r": 132.4785769871303,
        "risk_reward_ratio": "1:2"
      },
      "expert_commentary": {
        "technical": "JD.com RSI 58.8, MACD 2.66, trend bullish.",
        "volatility": "Annualized volatility 37.2% with ATR 3.0%.",
        "derivative": "Expected daily move HK$2.85; support HK$115.30, resistance HK$130.10."
      },
      "stale": false
    },
    "hsbc": {
      "price": 144.2,
      "open": 144.4,
      "high": 144.4,
      "low": 143.5,
      "volume": 6021644,
      "turnover": 868321064.8,
      "change": 0.3,
      "change_pct": 0.20848,
      "amplitude": 0.624133148404997,
      "ma_5": 141.75999755859374,
      "ma_10": 140.63017883300782,
      "ma_20": 140.51030578613282,
      "ma_50": 135.47544464111328,
      "ma_200": 135.14826939469677,
      "ema_12": 141.14837005897846,
      "ema_26": 139.872342205985,
      "rsi_14": 63.25873296423318,
      "rsi_6": 72.64154338466145,
      "macd": 1.276027852993451,
      "macd_signal": 1.148425067694106,
      "macd_histogram": 0.1276027852993451,
      "bb_upper": 144.5310956531766,
      "bb_middle": 140.51030578613282,
      "bb_lower": 136.48951591908903,
      "bb_width": 5.723124499015369,
      "atr": 2.8489620923189216,
      "volatility": 32.1756414997796,
      "historical_vol_20": 32.1756414997796,
      "historical_vol_60": 0.0,
      "momentum_10": 4.1141792204853385,
      "stoch_k": 97.5893898802322,
      "stoch_d": 97.5893898802322,
      "williams_r": -2.4106101197677967,
      "52w_high": 144.1999969482422,
      "52w_low": 118.81573486328125,
      "52w_position": 100.0,
      "avg_volume_20": 13108392.0,
      "volume_ratio": 0.4599224679884459,
      "support_levels": [
        135.9036102294922
      ],
      "resistance_levels": [
        144.1999969482422
      ],
      "market_cap_billion": 332,
      "market_cap_display": "$332B",
      "market_cap_hkd": "HK$2595B",
      "pe_ratio": 10.150784,
      "pb_ratio": 1.809552,
      "ps_ratio": 38.77397,
      "peg_ratio": 1.07,
      "ev_ebitda": 12.0,
      "fcf_yield": 0.0,
      "roe": 11.611,
      "roa": 0.722,
      "gross_margin": 0.0,
      "op_margin": 54.86299999999999,
      "net_margin": 34.977000000000004,
      "revenue_growth": 3.3000000000000003,
      "earnings_growth": 2.6,
      "revenue_billion": 63.773999104,
      "debt_equity": 0.0,
      "cash_billion": 1162.82097664,
      "net_cash_billion": 389.367988224,
      "fcf_billion": 0.0,
      "dividend_yield": 407.0,
      "beta": 0.574,
      "eps": 9.48,
      "source": {
        "quote": "akshare",
        "ohlcv": "yfinance",
        "fundamentals": "yfinance"
      },
      "confidence": {
        "quote": 0.95,
        "ohlcv": 0.85,
        "fundamentals": 0.8
      },
      "source_timestamp": "2026-05-26T05:56:25.923697",
      "last_verified_at": "2026-05-26T05:56:27.102542",
      "is_estimated": true,
      "estimated_fields": [
        "debt_equity",
        "ev_ebitda"
      ],
      "company_name": "HSBC",
      "symbol": "00005",
      "industry": "Banking / Financial Services",
      "sector": "Financials",
      "technical_rating": {
        "score": 3,
        "rating": "Buy",
        "color": "#4CAF50",
        "signals": [
          "Trend bullish",
          "MACD positive"
        ]
      },
      "derivative_analysis": {
        "daily_expected_move": 2.922753601761924,
        "atr_percent": 1.9757018670727613,
        "support_level": 135.9036102294922,
        "resistance_level": 144.1999969482422,
        "tight_stop_loss": 139.92655686152162,
        "target_1r": 148.47344313847836,
        "target_2r": 152.74688627695676,
        "risk_reward_ratio": "1:2"
      },
      "expert_commentary": {
        "technical": "HSBC RSI 63.3, MACD 1.28, trend bullish.",
        "volatility": "Annualized volatility 32.2% with ATR 2.0%.",
        "derivative": "Expected daily move HK$2.92; support HK$135.90, resistance HK$144.20."
      },
      "stale": false
    }
  },
  "schema_version": "v1"
}