{
  "timestamp": "2026-01-29T08:47:41.484271",
  "companies": {
    "tencent": {
      "price": 418.5,
      "market_cap_billion": 498,
      "market_cap_display": "$498B",
      "pe_ratio": 17.2,
      "pb_ratio": 3.7,
      "ps_ratio": 5.1,
      "52w_high": 476.8,
      "52w_low": 275.4,
      "roe": 13.8,
      "roa": 6.8,
      "gross_margin": 48.5,
      "op_margin": 28.5,
      "net_margin": 26.2,
      "revenue_growth": 8.5,
      "earnings_growth": 28.5,
      "revenue_billion": 620.5,
      "debt_equity": 0.08,
      "cash_billion": 95,
      "net_cash_billion": 72,
      "fcf_billion": 42.8,
      "dividend_yield": 0.8,
      "beta": 0.32
    },
    "alibaba": {
      "price": 131.2,
      "market_cap_billion": 363,
      "market_cap_display": "$363B",
      "pe_ratio": 18.4,
      "pb_ratio": 1.8,
      "ps_ratio": 1.9,
      "52w_high": 145.9,
      "52w_low": 71.25,
      "roe": 11.4,
      "roa": 5.3,
      "gross_margin": 40.0,
      "op_margin": 14.0,
      "net_margin": 13.1,
      "revenue_growth": 6.6,
      "earnings_growth": 273.2,
      "revenue_billion": 996.4,
      "debt_equity": 0.23,
      "cash_billion": 55,
      "net_cash_billion": 18,
      "fcf_billion": 19.0,
      "dividend_yield": 0.9,
      "beta": 0.21
    },
    "xiaomi": {
      "price": 43.35,
      "market_cap_billion": 190,
      "market_cap_display": "$190B",
      "pe_ratio": 36.0,
      "pb_ratio": 5.3,
      "ps_ratio": 3.1,
      "52w_high": 61.45,
      "52w_low": 12.56,
      "roe": 17.4,
      "roa": 4.8,
      "gross_margin": 21.6,
      "op_margin": 8.6,
      "net_margin": 8.7,
      "revenue_growth": 30.5,
      "earnings_growth": 133.5,
      "revenue_billion": 428.8,
      "debt_equity": 0.11,
      "cash_billion": 14,
      "net_cash_billion": 11,
      "fcf_billion": 59.3,
      "dividend_yield": 0.1,
      "beta": 1.01
    },
    "meituan": {
      "price": 102.4,
      "market_cap_billion": 80,
      "market_cap_display": "$80B",
      "pe_ratio": 19.8,
      "pb_ratio": 3.1,
      "ps_ratio": 1.6,
      "52w_high": 217.0,
      "52w_low": 101.6,
      "roe": 17.1,
      "roa": 5.2,
      "gross_margin": 26.0,
      "op_margin": 4.2,
      "net_margin": 2.4,
      "revenue_growth": 16.7,
      "earnings_growth": 57.2,
      "revenue_billion": 395.2,
      "debt_equity": 0.28,
      "cash_billion": 13,
      "net_cash_billion": 4,
      "fcf_billion": 5.1,
      "dividend_yield": 0.0,
      "beta": null
    }
  }
}
